Workbook

Sheet Unlevered cash flow
B1: ="Discounted Cash Flow "&'[1]Income Statement'!C3 -> Discounted Cash Flow
B3: Comfortdelgro Share Price | C3: 1.48
B4: Share Price Date | C4: 46022
B6: Unlevered Free Cash Flow (UFCF) in mm
B7: Fiscal Year | C7: =YEAR(C8) -> 2024 | D7: =YEAR(D8) -> 2025 | E7: =YEAR(E8) -> 2026 | F7: =YEAR(F8) -> 2027 | G7: =YEAR(G8) -> 2028 | H7: =YEAR(H8) -> 2029 | I7: =YEAR(I8) -> 2030
B8: Fiscal Year End Date | C8: 45657 | D8: 46022 | E8: =EDATE(D8,12) -> 46387 | F8: =EDATE(E8,12) -> 46752 | G8: =EDATE(F8,12) -> 47118 | H8: =EDATE(G8,12) -> 47483 | I8: =EDATE(H8,12) -> 47848
B9: Revenue | C9: ='Profit & loss'!C12 -> 4476.5 | D9: ='Profit & loss'!D12 -> 5058.6 | E9: 5240 | F9: 5350 | G9: ='Profit & loss'!G12 -> 5457 | H9: ='Profit & loss'!H12 -> 5566.14 | I9: ='Profit & loss'!I12 -> 5683.0289
B10: Operating Expenses:
B11: Staff costs | C11: =INDEX('Income Statement - Data'!$C$3:$D$33,MATCH($B11,'Income Statement - Data'!$B$3:$B$33,0),MATCH('Profit & loss'!C$11,'Income Statement - Data'!$C$2:$D$2,0)) -> -2024.1 | D11: =INDEX('Income Statement - Data'!$C$3:$D$33,MATCH($B11,'Income Statement - Data'!$B$3:$B$33,0),MATCH('Profit & loss'!D$11,'Income Statement - Data'!$C$2:$D$2,0)) -> -2272 | E11: ='Profit & loss'!E14 -> -2353.4733 | F11: ='Profit & loss'!F14 -> -2402.8783 | G11: ='Profit & loss'!G14 -> -2450.9358 | H11: ='Profit & loss'!H14 -> -2499.9545 | I11: ='Profit & loss'!I14 -> -2552.4536
B12: Contract services and subcontractor costs | C12: =INDEX('Income Statement - Data'!$C$3:$D$33,MATCH($B12,'Income Statement - Data'!$B$3:$B$33,0),MATCH('Profit & loss'!C$11,'Income Statement - Data'!$C$2:$D$2,0)) -> -445.8 | D12: =INDEX('Income Statement - Data'!$C$3:$D$33,MATCH($B12,'Income Statement - Data'!$B$3:$B$33,0),MATCH('Profit & loss'!D$11,'Income Statement - Data'!$C$2:$D$2,0)) -> -644.3 | E12: ='Profit & loss'!E15 -> -667.40442 | F12: ='Profit & loss'!F15 -> -681.41482 | G12: ='Profit & loss'!G15 -> -695.04311 | H12: ='Profit & loss'!H15 -> -708.94398 | I12: ='Profit & loss'!I15 -> -723.8318
B13: Fuel and electricity costs | C13: =INDEX('Income Statement - Data'!$C$3:$D$33,MATCH($B13,'Income Statement - Data'!$B$3:$B$33,0),MATCH('Profit & loss'!C$11,'Income Statement - Data'!$C$2:$D$2,0)) -> -397.2 | D13: =INDEX('Income Statement - Data'!$C$3:$D$33,MATCH($B13,'Income Statement - Data'!$B$3:$B$33,0),MATCH('Profit & loss'!D$11,'Income Statement - Data'!$C$2:$D$2,0)) -> -350.9 | E13: ='Profit & loss'!E16 -> -363.48318 | F13: ='Profit & loss'!F16 -> -371.11355 | G13: ='Profit & loss'!G16 -> -378.53582 | H13: ='Profit & loss'!H16 -> -386.10654 | I13: ='Profit & loss'!I16 -> -394.21477
B14: Repairs and maintenance costs | C14: =INDEX('Income Statement - Data'!$C$3:$D$33,MATCH($B14,'Income Statement - Data'!$B$3:$B$33,0),MATCH('Profit & loss'!C$11,'Income Statement - Data'!$C$2:$D$2,0)) -> -329.7 | D14: =INDEX('Income Statement - Data'!$C$3:$D$33,MATCH($B14,'Income Statement - Data'!$B$3:$B$33,0),MATCH('Profit & loss'!D$11,'Income Statement - Data'!$C$2:$D$2,0)) -> -349.3 | E14: ='Profit & loss'!E17 -> -361.8258 | F14: ='Profit & loss'!F17 -> -369.42138 | G14: ='Profit & loss'!G17 -> -376.80981 | H14: ='Profit & loss'!H17 -> -384.34601 | I14: ='Profit & loss'!I17 -> -392.41727
B15: Materials and consumables costs | C15: =INDEX('Income Statement - Data'!$C$3:$D$33,MATCH($B15,'Income Statement - Data'!$B$3:$B$33,0),MATCH('Profit & loss'!C$11,'Income Statement - Data'!$C$2:$D$2,0)) -> -104.4 | D15: =INDEX('Income Statement - Data'!$C$3:$D$33,MATCH($B15,'Income Statement - Data'!$B$3:$B$33,0),MATCH('Profit & loss'!D$11,'Income Statement - Data'!$C$2:$D$2,0)) -> -90 | E15: ='Profit & loss'!E18 -> -93.227375 | F15: ='Profit & loss'!F18 -> -95.184438 | G15: ='Profit & loss'!G18 -> -97.088127 | H15: ='Profit & loss'!H18 -> -99.02989 | I15: ='Profit & loss'!I18 -> -101.10952
B16: Insurance premiums and accident claims | C16: =INDEX('Income Statement - Data'!$C$3:$D$33,MATCH($B16,'Income Statement - Data'!$B$3:$B$33,0),MATCH('Profit & loss'!C$11,'Income Statement - Data'!$C$2:$D$2,0)) -> -102.1 | D16: =INDEX('Income Statement - Data'!$C$3:$D$33,MATCH($B16,'Income Statement - Data'!$B$3:$B$33,0),MATCH('Profit & loss'!D$11,'Income Statement - Data'!$C$2:$D$2,0)) -> -122.6 | E16: ='Profit & loss'!E19 -> -126.9964 | F16: ='Profit & loss'!F19 -> -129.66236 | G16: ='Profit & loss'!G19 -> -132.2556 | H16: ='Profit & loss'!H19 -> -134.90072 | I16: ='Profit & loss'!I19 -> -137.73363
B17: Premises costs | C17: =INDEX('Income Statement - Data'!$C$3:$D$33,MATCH($B17,'Income Statement - Data'!$B$3:$B$33,0),MATCH('Profit & loss'!C$11,'Income Statement - Data'!$C$2:$D$2,0)) -> -86.8 | D17: =INDEX('Income Statement - Data'!$C$3:$D$33,MATCH($B17,'Income Statement - Data'!$B$3:$B$33,0),MATCH('Profit & loss'!D$11,'Income Statement - Data'!$C$2:$D$2,0)) -> -97.5 | E17: ='Profit & loss'!E20 -> -100.99632 | F17: ='Profit & loss'!F20 -> -103.11647 | G17: ='Profit & loss'!G20 -> -105.1788 | H17: ='Profit & loss'!H20 -> -107.28238 | I17: ='Profit & loss'!I20 -> -109.53531
B18: Road tax and licence fees | C18: =INDEX('Income Statement - Data'!$C$3:$D$33,MATCH($B18,'Income Statement - Data'!$B$3:$B$33,0),MATCH('Profit & loss'!C$11,'Income Statement - Data'!$C$2:$D$2,0)) -> -74.6 | D18: =INDEX('Income Statement - Data'!$C$3:$D$33,MATCH($B18,'Income Statement - Data'!$B$3:$B$33,0),MATCH('Profit & loss'!D$11,'Income Statement - Data'!$C$2:$D$2,0)) -> -85.7 | E18: ='Profit & loss'!E21 -> -88.773178 | F18: ='Profit & loss'!F21 -> -90.636737 | G18: ='Profit & loss'!G21 -> -92.449472 | H18: ='Profit & loss'!H21 -> -94.298462 | I18: ='Profit & loss'!I21 -> -96.278729
B19: Utilities,It and communication costs | C19: =INDEX('Income Statement - Data'!$C$3:$D$33,MATCH($B19,'Income Statement - Data'!$B$3:$B$33,0),MATCH('Profit & loss'!C$11,'Income Statement - Data'!$C$2:$D$2,0)) -> -73.5 | D19: =INDEX('Income Statement - Data'!$C$3:$D$33,MATCH($B19,'Income Statement - Data'!$B$3:$B$33,0),MATCH('Profit & loss'!D$11,'Income Statement - Data'!$C$2:$D$2,0)) -> -90.6 | E19: ='Profit & loss'!E22 -> -93.848891 | F19: ='Profit & loss'!F22 -> -95.819001 | G19: ='Profit & loss'!G22 -> -97.735381 | H19: ='Profit & loss'!H22 -> -99.690089 | I19: ='Profit & loss'!I22 -> -101.78358
B20: Taxi drivers’ benefits | C20: =INDEX('Income Statement - Data'!$C$3:$D$33,MATCH($B20,'Income Statement - Data'!$B$3:$B$33,0),MATCH('Profit & loss'!C$11,'Income Statement - Data'!$C$2:$D$2,0)) -> -12 | D20: =INDEX('Income Statement - Data'!$C$3:$D$33,MATCH($B20,'Income Statement - Data'!$B$3:$B$33,0),MATCH('Profit & loss'!D$11,'Income Statement - Data'!$C$2:$D$2,0)) -> -70.4 | E20: ='Profit & loss'!E23 -> -72.924525 | F20: ='Profit & loss'!F23 -> -74.455383 | G20: ='Profit & loss'!G23 -> -75.944491 | H20: ='Profit & loss'!H23 -> -77.46338 | I20: ='Profit & loss'!I23 -> -79.090111
B21: Advertising production and promotion costs | C21: =INDEX('Income Statement - Data'!$C$3:$D$33,MATCH($B21,'Income Statement - Data'!$B$3:$B$33,0),MATCH('Profit & loss'!C$11,'Income Statement - Data'!$C$2:$D$2,0)) -> -34.5 | D21: =INDEX('Income Statement - Data'!$C$3:$D$33,MATCH($B21,'Income Statement - Data'!$B$3:$B$33,0),MATCH('Profit & loss'!D$11,'Income Statement - Data'!$C$2:$D$2,0)) -> -36 | E21: ='Profit & loss'!E24 -> -37.29095 | F21: ='Profit & loss'!F24 -> -38.073775 | G21: ='Profit & loss'!G24 -> -38.835251 | H21: ='Profit & loss'!H24 -> -39.611956 | I21: ='Profit & loss'!I24 -> -40.443807
B22: Professional fees | C22: =INDEX('Income Statement - Data'!$C$3:$D$33,MATCH($B22,'Income Statement - Data'!$B$3:$B$33,0),MATCH('Profit & loss'!C$11,'Income Statement - Data'!$C$2:$D$2,0)) -> -33.2 | D22: =INDEX('Income Statement - Data'!$C$3:$D$33,MATCH($B22,'Income Statement - Data'!$B$3:$B$33,0),MATCH('Profit & loss'!D$11,'Income Statement - Data'!$C$2:$D$2,0)) -> -30.8 | E22: ='Profit & loss'!E25 -> -31.90448 | F22: ='Profit & loss'!F25 -> -32.57423 | G22: ='Profit & loss'!G25 -> -33.225715 | H22: ='Profit & loss'!H25 -> -33.890229 | I22: ='Profit & loss'!I25 -> -34.601924
... B25: Other operating costs | C25: =INDEX('Income Statement - Data'!$C$3:$D$33,MATCH($B25,'Income Statement - Data'!$B$3:$B$33,0),MATCH('Profit & loss'!C$11,'Income Statement - Data'!$C$2:$D$2,0)) -> -72.4 | D25: =INDEX('Income Statement - Data'!$C$3:$D$33,MATCH($B25,'Income Statement - Data'!$B$3:$B$33,0),MATCH('Profit & loss'!D$11,'Income Statement - Data'!$C$2:$D$2,0)) -> -69.7 | E25: ='Profit & loss'!E28 -> -72.199423 | F25: ='Profit & loss'!F28 -> -73.71506 | G25: ='Profit & loss'!G28 -> -75.189361 | H25: ='Profit & loss'!H28 -> -76.693148 | I25: ='Profit & loss'!I28 -> -78.303704
B26: EBITDA | C26: =SUM(C9:C25) -> 691.3 | D26: =SUM(D9:D25) -> 772.6 | E26: =SUM(E9:E25) -> 773.47646 | F26: =SUM(F9:F25) -> 789.71356 | G26: =SUM(G9:G25) -> 805.50783 | H26: =SUM(H9:H25) -> 821.61798 | I26: =SUM(I9:I25) -> 838.87196
B27: Depreciation and Amortization | C27: ='Profit & loss'!C32 -> -368.4 | D27: ='Profit & loss'!D32 -> -399.6 | E27: ='Profit & loss'!E32 -> -437.32044 | F27: ='Profit & loss'!F32 -> -471.88961 | G27: ='Profit & loss'!G32 -> -502.70317 | H27: ='Profit & loss'!H32 -> -530.38301 | I27: ='Profit & loss'!I32 -> -555.55293
B28: EBIT | C28: =SUM(C26:C27) -> 322.9 | D28: =SUM(D26:D27) -> 373 | E28: =SUM(E26:E27) -> 336.15601 | F28: =SUM(F26:F27) -> 317.82395 | G28: =SUM(G26:G27) -> 302.80466 | H28: =SUM(H26:H27) -> 291.23498 | I28: =SUM(I26:I27) -> 283.31904
B29: Taxation | C29: ='Profit & loss'!C40 -> -61.8 | D29: ='Profit & loss'!D40 -> -69.5 | E29: ='Profit & loss'!E40 -> -57.270983 | F29: ='Profit & loss'!F40 -> -53.712682 | G29: ='Profit & loss'!G40 -> -50.811483 | H29: ='Profit & loss'!H40 -> -48.59892 | I29: ='Profit & loss'!I40 -> -47.120317
B30: NOPAT (Net Operating Profit After Taxes) | C30: =C28*(1-WACC!$D$6) -> 258.60751 | D30: =D28*(1-WACC!$D$6) -> 298.73212 | E30: =E28*(1-WACC!$D$6) -> 269.22412 | F30: =F28*(1-WACC!$D$6) -> 254.54215 | G30: =G28*(1-WACC!$D$6) -> 242.51335 | H30: =H28*(1-WACC!$D$6) -> 233.2473 | I30: =I28*(1-WACC!$D$6) -> 226.9075
B31: (+) Depreciation & Amortization | D31: =-D27 -> 399.6 | E31: =-E27 -> 437.32044 | F31: =-F27 -> 471.88961 | G31: =-G27 -> 502.70317 | H31: =-H27 -> 530.38301 | I31: =-I27 -> 555.55293
B32: (-) Capital Expenditures | D32: =-'Fixed assets schedule'!D4 -> -583.3 | E32: =-'Fixed assets schedule'!E4 -> -604.21698 | F32: =-'Fixed assets schedule'!F4 -> -616.90092 | G32: =-'Fixed assets schedule'!G4 -> -629.23894 | H32: =-'Fixed assets schedule'!H4 -> -641.82372 | I32: =-'Fixed assets schedule'!I4 -> -655.30202
B33: (-) Change in NWC | D33: =C34-D34 -> -64.8 | E33: =D34-E34 -> -2.2304748 | F33: =E34-F34 -> -1.3525481 | G33: =F34-G34 -> -1.3156605 | H33: =G34-H34 -> -1.3419737 | I33: =H34-I34 -> -1.4372538
B34: NWC | C34: =C35-C36 -> -132.7 | D34: =D35-D36 -> -67.9 | E34: =E35-E36 -> -65.669525 | F34: =F35-F36 -> -64.316977 | G34: =G35-G36 -> -63.001317 | H34: =H35-H36 -> -61.659343 | I34: =I35-I36 -> -60.222089
B35: Current Assets | C35: ='balance sheet'!G11-'balance sheet'!G6 -> 1006.7 | D35: ='balance sheet'!H11-'balance sheet'!H6 -> 1016.4 | E35: ='balance sheet'!I11-'balance sheet'!I6 -> 1052.8478 | F35: ='balance sheet'!J11-'balance sheet'!J6 -> 1074.9496 | G35: ='balance sheet'!K11-'balance sheet'!K6 -> 1096.4486 | H35: ='balance sheet'!L11-'balance sheet'!L6 -> 1118.3776 | I35: ='balance sheet'!M11-'balance sheet'!M6 -> 1141.8635
B36: Current Liabilitites | C36: ='balance sheet'!G35-'balance sheet'!G27-'balance sheet'!G28-'balance sheet'!G29 -> 1139.4 | D36: ='balance sheet'!H35-'balance sheet'!H27-'balance sheet'!H28-'balance sheet'!H29 -> 1084.3 | E36: ='balance sheet'!I35-'balance sheet'!I27-'balance sheet'!I28-'balance sheet'!I29 -> 1118.5173 | F36: ='balance sheet'!J35-'balance sheet'!J27-'balance sheet'!J28-'balance sheet'!J29 -> 1139.2666 | G36: ='balance sheet'!K35-'balance sheet'!K27-'balance sheet'!K28-'balance sheet'!K29 -> 1159.4499 | H36: ='balance sheet'!L35-'balance sheet'!L27-'balance sheet'!L28-'balance sheet'!L29 -> 1180.0369 | I36: ='balance sheet'!M35-'balance sheet'!M27-'balance sheet'!M28-'balance sheet'!M29 -> 1202.0856
B37: Unlevered Free Cash Flow | D37: =D30+D31+D32+D33 -> 50.232121 | E37: =E30+E31+E32+E33 -> 100.09712 | F37: =F30+F31+F32+F33 -> 108.17829 | G37: =G30+G31+G32+G33 -> 114.66192 | H37: =H30+H31+H32+H33 -> 120.46461 | I37: =I30+I31+I32+I33 -> 125.72115
B41: Unlevered Free Cash Flow (UFCF) in mm
B42: Fiscal Year | C42: =YEAR(C43) -> 2024 | D42: =YEAR(D43) -> 2025 | E42: =YEAR(E43) -> 2026 | F42: =YEAR(F43) -> 2027 | G42: =YEAR(G43) -> 2028 | H42: =YEAR(H43) -> 2029 | I42: =YEAR(I43) -> 2030
B43: Fiscal Year End Date | C43: 45657 | D43: 46022 | E43: =EDATE(D43,12) -> 46387 | F43: =EDATE(E43,12) -> 46752 | G43: =EDATE(F43,12) -> 47118 | H43: =EDATE(G43,12) -> 47483 | I43: =EDATE(H43,12) -> 47848
B44: UFCF | E44: =E37 -> 100.09712 | F44: =F37 -> 108.17829 | G44: =G37 -> 114.66192 | H44: =H37 -> 120.46461 | I44: =I37 -> 125.72115
B45: Period | E45: 1 | F45: 2 | G45: 3 | H45: 4 | I45: 5
B46: PV of UFCF | E46: =E37/(1+WACC!D18)^1 -> 96.032479 | F46: =F44/(1+WACC!$D$18)^'Unlevered cash flow'!F45 -> 99.571088 | G46: =G44/(1+WACC!$D$18)^'Unlevered cash flow'!G45 -> 101.25323 | H46: =H44/(1+WACC!$D$18)^'Unlevered cash flow'!H45 -> 102.0577 | I46: =I44/(1+WACC!$D$18)^'Unlevered cash flow'!I45 -> 102.18596
B48: Sum of pv | C48: =SUM(E46:I46) -> 501.10046
B52: Terminal Value Exit Multiple Method | F52: Terminal Value Growth Perpetuity Method
B53: Sum of PV of FCF | C53: =SUM(E46:I46) -> 501.10046 | F53: Sum of PV of FCF | I53: =C48 -> 501.10046
B54: Exit EBITDA | C54: =I26 -> 838.87196 | F54: Growth Rate | I54: 0.02
B55: Exit Multiple (EV / EBITDA) | C55: ='COMPARABLE COMPANIES'!B6 -> 2.8482165 | F55: WACC | I55: =WACC!D18 -> 0.04232566
B56: WACC | C56: =WACC!D18 -> 0.04232566 | F56: Terminal Year FCF | I56: =I44*(1+I54) -> 128.23558
B57: Terminal Value | C57: =C54*C55 -> 2389.289 | F57: Terminal Value | I57: =I56/(I55-I54) -> 5743.8651
B58: PV of Terminal Value | C58: =C57/(1+C56)^$I$45 -> 1942.0103 | F58: PV of Terminal Value | I58: =I57/(1+I55)^I45 -> 4668.6045
B59: Enterprise Value | C59: =C58+C53 -> 2443.1108 | F59: Enterprise Value | I59: =I58+I53 -> 5169.7049
B61: Enterprise Value to Equity Value | F61: Diluted shares oustanding
B62: Enterprise Value | C62: =I59 -> 5169.7049 | F62: Basic shares oustanding | G62: 2166763244
B63: + Cash & Cash Equivalents | C63: ='balance sheet'!H6 -> 868.4 | F63: treasury shares | G63: 684669
B64: - Debt (ST + LT) | C64: =SUM('balance sheet'!H27:H29,'balance sheet'!H38:H40) -> 1821.5 | F64: options | G64: 0
B65: - Minority Interest | C65: ='balance sheet'!H56 -> 385.2 | F65: convertibles | G65: 0
B66: - Preferred Stock | C66: 0 | F66: Diluted shares outstanding | G66: =SUM(G62:G65) -> 2167447913
B67: - Convertible Debt | C67: 0
B68: Equity Value | C68: =C62+C63-C64-C65 -> 3831.4049
B69: Shares Outstanding | C69: =G66 -> 2167447913
B70: Implied Share Price | C70: =C68*1000000/C69 -> 1.7677033
B75: Sensitivity table
D78: Terminal growth
A79: WACC | B79: =C70 -> 1.7677033 | C79: =D79-1 -> 0.8482165 | D79: =E79-1 -> 1.8482165 | E79: =C55 -> 2.8482165 | F79: =E79+1 -> 3.8482165 | G79: =F79+1 -> 4.8482165
B80: =B81+0.01 -> 0.06232566 | C80: 1.7677033 | D80: 1.7677033 | E80: 1.7677033 | F80: 1.7677033 | G80: 1.7677033
B81: =B82+0.01 -> 0.05232566 | C81: 1.7677033 | D81: 1.7677033 | E81: 1.7677033 | F81: 1.7677033 | G81: 1.7677033
B82: =I55 -> 0.04232566 | C82: 1.7677033 | D82: 1.7677033 | E82: 1.7677033 | F82: 1.7677033 | G82: 1.7677033
B83: =B82-0.01 -> 0.03232566 | C83: 1.7677033 | D83: 1.7677033 | E83: 1.7677033 | F83: 1.7677033 | G83: 1.7677033
B84: =B83-0.01 -> 0.02232566 | C84: 1.7677033 | D84: 1.7677033 | E84: 1.7677033 | F84: 1.7677033 | G84: 1.7677033

Sheet WACC
B2: Weighted Average Cost of Capital
B4: Cost of Debt | F4: Cost of Equity
B5: Cost of debt | D5: =-'Profit & loss'!D37/('debt schedule'!C5+'debt schedule'!C11) -> 0.028987099 | F5: Risk free rate | G5: 0.028
B6: Tax Rate | D6: ='Profit & loss'!E105 -> 0.1991096 | F6: Beta | G6: ='beta calculation'!Q5 -> 0.59520093
B7: After tax cost of debt | D7: =D5*(1-D6) -> 0.023215489 | F7: Market risk premium | H7: 0.0423
F8: Cost of equity | H8: =G5+G6*H7 -> 0.053176999
B10: Capital Structure Weights
B12: Equity | D12: =2167447913*'Unlevered cash flow'!C3 -> 3.2078229e+09
B13: Debt | D13: =('debt schedule'!C5+'debt schedule'!C11)*1000000 -> 1.8215e+09
B14: total | D14: =SUM(D12:D13) -> 5.0293229e+09
B16: Equity weight | D16: =D12/D14 -> 0.63782401
B17: debt weight | D17: =D13/D14 -> 0.36217599
B18: Weighted Average Cost of Capital (WACC) | D18: =D16*H8+D17*D7 -> 0.04232566

Sheet COMPARABLE COMPANIES
A1: Company Names | B1: EV/ EBITDA
A2: Mobico Group plc | B2: =F4/F3 -> 2.8482165 | E2: Mobico Group plc
A3: FirstGroup plc | B3: =F8/F7 -> 2.3947861 | E3: EBITDA | F3: =464.8*1000000 -> 464800000
A4: kelsian group limited | B4: =F13/F12 -> 6.6296784 | E4: EV | F4: =(614086377*17.4/100)+(1249000000+346300000)-425600000+47300000 -> 1.323851e+09
A5: Average EV/ EBITDA | B5: =AVERAGE(B2:B4) -> 3.9575603
A6: Median EV/ EBITDA | B6: =MEDIAN(B2:B4) -> 2.8482165 | E6: FirstGroup plc
E7: EBITDA | F7: =702.9*1000000 -> 702900000
E8: EV | F8: =(570695015*1.662)+(447100000+710200000)-432000000+9500000 -> 1.6832951e+09
E11: kelsian group limited
E12: EBITDA | F12: =315792*1000 -> 315792000
E13: EV | F13: =(271656692*4.47)+(9838000+42313000+801903000+68873000+132694000)-176330000+3000 -> 2.0935994e+09

Sheet beta calculation
A1: STI: | I1: COMFORTDELGRO | S1: Kelsian Group | AB1: First Group plc | AK1: Mobico Group plc
A2: Date | B2: Price | C2: Open | D2: High | E2: Low | F2: Vol. | G2: returns % | I2: Date | J2: Price | K2: Open | L2: High | M2: Low | N2: Vol. | O2: returns % | P2: levered historical beta: | Q2: =SLOPE(O3:O63,G3:G63) -> 0.56673749 | S2: Date | T2: Price | U2: Open | V2: High | W2: Low | X2: Vol. | Y2: Change % | Z2: beta: | AA2: =SLOPE(Y3:Y63,G3:G63) -> 0.75171246 | AB2: Date | AC2: Price | AD2: Open | AE2: High | AF2: Low | AG2: Vol. | AH2: Change % | AI2: beta | AJ2: =SLOPE(AH3:AH63,G3:G63) -> 0.34260011 | AK2: Date | AL2: Price | AM2: Open | AN2: High | AO2: Low | AP2: Vol. | AQ2: Change % | AS2: beta | AT2: =SLOPE(AQ3:AQ63,G3:G63) -> 1.9065593
A3: 46023 | B3: 4905.13 | C3: 4652.34 | D3: 4933.88 | E3: 4648.38 | F3: 4.86B | G3: 0.0557 | I3: 46023 | J3: 1.47 | K3: 1.48 | L3: 1.49 | M3: 1.45 | N3: 152.91M | O3: -0.0068 | S3: 46023 | T3: 3.9 | U3: 4.25 | V3: 4.4 | W3: 3.86 | X3: 8.04M | Y3: -0.0824 | Z3: unlevered beta: | AA3: =AA2/(1+(1-0.2049)*(9838+42313+801903+68873+132694)/(952614)) -> 0.39961858 | AB3: 46023 | AC3: 186.4 | AD3: 190.6 | AE3: 198.3 | AF3: 180 | AG3: 34.88M | AH3: -0.022 | AI3: unlevered beta: | AJ3: =AJ2/(1+(1-0.238)*(447.1+710.2)/(719.5)) -> 0.1539319 | AK3: 46023 | AL3: 23.26 | AM3: 23.4 | AN3: 27.62 | AO3: 20.8 | AP3: 80.38M | AQ3: 0.0087 | AS3: unlevered beta: | AT3: =AT2/(1-(1-0.47759)*(1249+346.3)/(-352.3)) -> 0.56648432
A4: 45669 | B4: 4646.21 | C4: 4531.55 | D4: 4665.12 | E4: 4492.46 | F4: 4.26B | G4: 0.027 | I4: 45669 | J4: 1.48 | K4: 1.45 | L4: 1.48 | M4: 1.42 | N4: 119.00M | O4: 0.0278 | P4: median unlevered beta of comparable companies | Q4: =MEDIAN(AA3,AJ3,AT3) -> 0.39961858 | S4: 45669 | T4: 4.25 | U4: 4.65 | V4: 4.65 | W4: 4.16 | X4: 8.47M | Y4: -0.0801 | AB4: 45669 | AC4: 190.6 | AD4: 175.6 | AE4: 199.7 | AF4: 173.5 | AG4: 20.15M | AH4: 0.0787 | AK4: 45669 | AL4: 23.06 | AM4: 21.46 | AN4: 25.32 | AO4: 21 | AP4: 49.04M | AQ4: 0.0501
A5: 45668 | B5: 4523.96 | C5: 4437.38 | D5: 4575.91 | E5: 4372.64 | F5: 6.64B | G5: 0.0215 | I5: 45668 | J5: 1.44 | K5: 1.46 | L5: 1.49 | M5: 1.44 | N5: 177.74M | O5: -0.0137 | P5: relevered beta | Q5: =Q4*(1+(1-'Profit & loss'!E105)*('debt schedule'!C5+'debt schedule'!C11)/('balance sheet'!H57)) -> 0.59520093 | S5: 45668 | T5: 4.62 | U5: 4.7 | V5: 4.87 | W5: 4.35 | X5: 12.61M | Y5: -0.0513 | AB5: 45668 | AC5: 176.7 | AD5: 214 | AE5: 214 | AF5: 171.3 | AG5: 30.33M | AH5: -0.1586 | AK5: 45668 | AL5: 21.96 | AM5: 26 | AN5: 27.08 | AO5: 19 | AP5: 69.44M | AQ5: -0.1637
A6: 45667 | B6: 4428.62 | C6: 4307.76 | D6: 4478.15 | E6: 4307.76 | F6: 6.02B | G6: 0.0299 | I6: 45667 | J6: 1.46 | K6: 1.45 | L6: 1.5 | M6: 1.44 | N6: 244.31M | O6: 0.0069 | S6: 45667 | T6: 4.87 | U6: 4.81 | V6: 5.22 | W6: 4.71 | X6: 8.68M | Y6: -0.0081 | AB6: 45667 | AC6: 210 | AD6: 224.6 | AE6: 225.6 | AF6: 198.8 | AG6: 40.40M | AH6: -0.0691 | AK6: 45667 | AL6: 26.26 | AM6: 28.46 | AN6: 30.76 | AO6: 25.24 | AP6: 73.77M | AQ6: -0.0863
A7: 45666 | B7: 4300.16 | C7: 4270.86 | D7: 4375.33 | E7: 4252.27 | F7: 5.89B | G7: 0.0071 | I7: 45666 | J7: 1.45 | K7: 1.45 | L7: 1.51 | M7: 1.44 | N7: 241.76M | O7: 0 | S7: 45666 | T7: 4.91 | U7: 4.84 | V7: 5.2 | W7: 4.75 | X7: 14.48M | Y7: -0.0141 | AB7: 45666 | AC7: 225.6 | AD7: 221 | AE7: 225.6 | AF7: 210.2 | AG7: 22.11M | AH7: 0.0181 | AK7: 45666 | AL7: 28.74 | AM7: 32.98 | AN7: 33.32 | AO7: 24.36 | AP7: 125.76M | AQ7: -0.1243
A8: 45665 | B8: 4269.7 | C8: 4169.28 | D8: 4282.8 | E8: 4144.89 | F8: 5.83B | G8: 0.023 | I8: 45665 | J8: 1.45 | K8: 1.53 | L8: 1.6 | M8: 1.42 | N8: 338.76M | O8: -0.0523 | S8: 45665 | T8: 4.98 | U8: 3.73 | V8: 5.11 | W8: 3.63 | X8: 12.49M | Y8: 0.3316 | AB8: 45665 | AC8: 221.6 | AD8: 223.6 | AE8: 240.4 | AF8: 215.2 | AG8: 21.66M | AH8: -0.0125 | AK8: 45665 | AL8: 32.82 | AM8: 35.66 | AN8: 38.12 | AO8: 32.64 | AP8: 98.06M | AQ8: -0.0964
A9: 45664 | B9: 4173.77 | C9: 3972.18 | D9: 4274.32 | E9: 3968.57 | F9: 6.39B | G9: 0.0528 | I9: 45664 | J9: 1.53 | K9: 1.43 | L9: 1.64 | M9: 1.4 | N9: 379.98M | O9: 0.0699 | S9: 45664 | T9: 3.74 | U9: 3.79 | V9: 3.92 | W9: 3.68 | X9: 8.91M | Y9: -0.0132 | AB9: 45664 | AC9: 224.4 | AD9: 229.6 | AE9: 238 | AF9: 204.2 | AG9: 37.23M | AH9: -0.0269 | AK9: 45664 | AL9: 36.32 | AM9: 29.2 | AN9: 40.38 | AO9: 28 | AP9: 109.97M | AQ9: 0.2312
A10: 45663 | B10: 3964.29 | C10: 3904.42 | D10: 3971.7 | E10: 3845.78 | F10: 5.53B | G10: 0.0179 | I10: 45663 | J10: 1.43 | K10: 1.43 | L10: 1.45 | M10: 1.4 | N10: 184.35M | O10: 0.007 | S10: 45663 | T10: 3.79 | U10: 3.2 | V10: 3.88 | W10: 3.11 | X10: 24.50M | Y10: 0.1698 | AB10: 45663 | AC10: 230.6 | AD10: 191.6 | AE10: 238 | AF10: 189.7 | AG10: 41.26M | AH10: 0.2073 | AK10: 45663 | AL10: 29.5 | AM10: 30.24 | AN10: 32.74 | AO10: 25.24 | AP10: 153.28M | AQ10: -0.0134
A11: 45662 | B11: 3894.61 | C11: 3842.38 | D11: 3956.26 | E11: 3831.04 | F11: 5.68B | G11: 0.0162 | I11: 45662 | J11: 1.42 | K11: 1.53 | L11: 1.54 | M11: 1.39 | N11: 193.71M | O11: -0.0719 | S11: 45662 | T11: 3.24 | U11: 2.72 | V11: 3.35 | W11: 2.68 | X11: 19.24M | Y11: 0.1956 | AB11: 45662 | AC11: 191 | AD11: 180.8 | AE11: 194.2 | AF11: 172.1 | AG11: 26.64M | AH11: 0.106 | AK11: 45662 | AL11: 29.9 | AM11: 30.26 | AN11: 32.78 | AO11: 26.92 | AP11: 96.48M | AQ11: -0.0386
A12: 45661 | B12: 3832.51 | C12: 3950.77 | D12: 3980.28 | E12: 3372.38 | F12: 8.12B | G12: -0.0352 | I12: 45661 | J12: 1.53 | K12: 1.45 | L12: 1.55 | M12: 1.36 | N12: 247.71M | O12: 0.0479 | S12: 45661 | T12: 2.71 | U12: 2.68 | V12: 2.77 | W12: 2.19 | X12: 25.14M | Y12: 0.0112 | AB12: 45661 | AC12: 172.7 | AD12: 159.5 | AE12: 174.2 | AF12: 137.8 | AG12: 20.37M | AH12: 0.1071 | AK12: 45661 | AL12: 31.1 | AM12: 58.9 | AN12: 62.8 | AO12: 28.66 | AP12: 82.69M | AQ12: -0.4652
A13: 45660 | B13: 3972.43 | C13: 3895.37 | D13: 4005.18 | E13: 3805.7 | F13: 6.27B | G13: 0.0197 | I13: 45660 | J13: 1.46 | K13: 1.39 | L13: 1.48 | M13: 1.38 | N13: 190.45M | O13: 0.0504 | S13: 45660 | T13: 2.68 | U13: 3.11 | V13: 3.55 | W13: 2.65 | X13: 27.04M | Y13: -0.1355 | AB13: 45660 | AC13: 156 | AD13: 159.1 | AE13: 184.8 | AF13: 156 | AG13: 52.52M | AH13: -0.0232 | AK13: 45660 | AL13: 58.15 | AM13: 66.9 | AN13: 72.55 | AO13: 57 | AP13: 29.08M | AQ13: -0.1467
A14: 45659 | B14: 3895.7 | C14: 3802.42 | D14: 3951.64 | E14: 3797.83 | F14: 6.22B | G14: 0.0103 | I14: 45659 | J14: 1.39 | K14: 1.41 | L14: 1.42 | M14: 1.34 | N14: 172.73M | O14: -0.0142 | S14: 45659 | T14: 3.1 | U14: 3.76 | V14: 3.92 | W14: 2.78 | X14: 15.66M | Y14: -0.1885 | AB14: 45659 | AC14: 159.7 | AD14: 169.9 | AE14: 170 | AF14: 153.6 | AG14: 28.37M | AH14: -0.0208 | AK14: 45659 | AL14: 68.15 | AM14: 73.5 | AN14: 73.5 | AO14: 67.55 | AP14: 20.33M | AQ14: -0.0728
A15: 45658 | B15: 3855.82 | C15: 3790.36 | D15: 3886.98 | E15: 3765.41 | F15: 4.58B | G15: 0.018 | I15: 45658 | J15: 1.41 | K15: 1.48 | L15: 1.48 | M15: 1.38 | N15: 86.72M | O15: -0.0473 | S15: 45658 | T15: 3.82 | U15: 3.66 | V15: 3.84 | W15: 3.41 | X15: 10.79M | Y15: 0.0437 | AB15: 45658 | AC15: 163.1 | AD15: 162.2 | AE15: 170 | AF15: 149 | AG15: 17.42M | AH15: 0.0149 | AK15: 45658 | AL15: 73.5 | AM15: 80 | AN15: 82.2 | AO15: 71.7 | AP15: 26.10M | AQ15: -0.0731
A16: 45303 | B16: 3787.6 | C16: 3760.39 | D16: 3842.71 | E16: 3715.52 | F16: 4.57B | G16: 0.0129 | I16: 45303 | J16: 1.48 | K16: 1.46 | L16: 1.5 | M16: 1.44 | N16: 61.42M | O16: 0.0137 | S16: 45303 | T16: 3.66 | U16: 3.94 | V16: 3.99 | W16: 3.45 | X16: 11.27M | Y16: -0.0615 | AB16: 45303 | AC16: 160.7 | AD16: 158.3 | AE16: 175 | AF16: 150.2 | AG16: 22.12M | AH16: 0.0614 | AK16: 45303 | AL16: 79.3 | AM16: 87 | AN16: 90.9 | AO16: 74.85 | AP16: 42.57M | AQ16: -0.0869
A17: 45302 | B17: 3739.29 | C17: 3527.13 | D17: 3766.93 | E17: 3524.33 | F17: 7.18B | G17: 0.0507 | I17: 45302 | J17: 1.46 | K17: 1.47 | L17: 1.5 | M17: 1.45 | N17: 85.98M | O17: -0.0068 | S17: 45302 | T17: 3.9 | U17: 3.84 | V17: 3.97 | W17: 3.69 | X17: 11.53M | Y17: -0.0051 | AB17: 45302 | AC17: 151.4 | AD17: 135 | AE17: 156.5 | AF17: 128.6 | AG17: 23.20M | AH17: 0.1358 | AK17: 45302 | AL17: 86.85 | AM17: 68 | AN17: 87 | AO17: 66.75 | AP17: 27.18M | AQ17: 0.2523
... A63: 44197 | B63: 2902.52 | C63: 2846.2 | D63: 3017.15 | E63: 2832.04 | F63: 5.21B | G63: 0.0206 | I63: 44197 | J63: 1.534 | K63: 1.631 | L63: 1.699 | M63: 1.534 | N63: 209.21M | O63: -0.0539 | S63: 44197 | T63: 6.36 | U63: 6.55 | V63: 6.84 | W63: 5.81 | X63: 3.94M | Y63: -0.0359 | AB63: 44197 | AC63: 71.75 | AD63: 76.05 | AE63: 81 | AF63: 66.5 | AG63: 62.05M | AH63: -0.0304 | AK63: 44197 | AL63: 250.2 | AM63: 243 | AN63: 273.42 | AO63: 222.81 | AP63: 47.82M | AQ63: 0.0539

Sheet Profit & loss
A1: Three sheet statement model ComfortDelgro
B5: Company name | C5: ComfortDelgro
B6: ticker | C6: C52
B7: Circuit break(0=on, 1=off)
B8: Fiscal year end date | C8: 46022
C9: Base case
B10: Income statement
B11: SGD in millions | C11: 2024 | D11: 2025 | E11: =D11+1 -> 2026 | F11: =E11+1 -> 2027 | G11: =F11+1 -> 2028 | H11: =G11+1 -> 2029 | I11: =H11+1 -> 2030
B12: Net Sales | C12: =INDEX('Income Statement - Data'!$C$3:$D$33,MATCH($B12,'Income Statement - Data'!$B$3:$B$33,0),MATCH('Profit & loss'!C$11,'Income Statement - Data'!$C$2:$D$2,0)) -> 4476.5 | D12: =INDEX('Income Statement - Data'!$C$3:$D$33,MATCH($B12,'Income Statement - Data'!$B$3:$B$33,0),MATCH('Profit & loss'!D$11,'Income Statement - Data'!$C$2:$D$2,0)) -> 5058.6 | E12: 5240 | F12: 5350 | G12: =F12*(1+G48) -> 5457 | H12: =G12*(1+H48) -> 5566.14 | I12: =H12*(1+I48) -> 5683.0289
B13: Operating expenses
B14: Staff costs | C14: =INDEX('Income Statement - Data'!$C$3:$D$33,MATCH($B14,'Income Statement - Data'!$B$3:$B$33,0),MATCH('Profit & loss'!C$11,'Income Statement - Data'!$C$2:$D$2,0)) -> -2024.1 | D14: =INDEX('Income Statement - Data'!$C$3:$D$33,MATCH($B14,'Income Statement - Data'!$B$3:$B$33,0),MATCH('Profit & loss'!D$11,'Income Statement - Data'!$C$2:$D$2,0)) -> -2272 | E14: =-$E53*E$12 -> -2353.4733 | F14: =-$E53*F$12 -> -2402.8783 | G14: =-$E53*G$12 -> -2450.9358 | H14: =-$E53*H$12 -> -2499.9545 | I14: =-$E53*I$12 -> -2552.4536
B15: Contract services and subcontractor costs | C15: =INDEX('Income Statement - Data'!$C$3:$D$33,MATCH($B15,'Income Statement - Data'!$B$3:$B$33,0),MATCH('Profit & loss'!C$11,'Income Statement - Data'!$C$2:$D$2,0)) -> -445.8 | D15: =INDEX('Income Statement - Data'!$C$3:$D$33,MATCH($B15,'Income Statement - Data'!$B$3:$B$33,0),MATCH('Profit & loss'!D$11,'Income Statement - Data'!$C$2:$D$2,0)) -> -644.3 | E15: =-$E58*E$12 -> -667.40442 | F15: =-$E58*F$12 -> -681.41482 | G15: =-$E58*G$12 -> -695.04311 | H15: =-$E58*H$12 -> -708.94398 | I15: =-$E58*I$12 -> -723.8318
B16: Fuel and electricity costs | C16: =INDEX('Income Statement - Data'!$C$3:$D$33,MATCH($B16,'Income Statement - Data'!$B$3:$B$33,0),MATCH('Profit & loss'!C$11,'Income Statement - Data'!$C$2:$D$2,0)) -> -397.2 | D16: =INDEX('Income Statement - Data'!$C$3:$D$33,MATCH($B16,'Income Statement - Data'!$B$3:$B$33,0),MATCH('Profit & loss'!D$11,'Income Statement - Data'!$C$2:$D$2,0)) -> -350.9 | E16: =-$E63*E$12 -> -363.48318 | F16: =-$E63*F$12 -> -371.11355 | G16: =-$E63*G$12 -> -378.53582 | H16: =-$E63*H$12 -> -386.10654 | I16: =-$E63*I$12 -> -394.21477
B17: Repairs and maintenance costs | C17: =INDEX('Income Statement - Data'!$C$3:$D$33,MATCH($B17,'Income Statement - Data'!$B$3:$B$33,0),MATCH('Profit & loss'!C$11,'Income Statement - Data'!$C$2:$D$2,0)) -> -329.7 | D17: =INDEX('Income Statement - Data'!$C$3:$D$33,MATCH($B17,'Income Statement - Data'!$B$3:$B$33,0),MATCH('Profit & loss'!D$11,'Income Statement - Data'!$C$2:$D$2,0)) -> -349.3 | E17: =-$E68*E$12 -> -361.8258 | F17: =-$E68*F$12 -> -369.42138 | G17: =-$E68*G$12 -> -376.80981 | H17: =-$E68*H$12 -> -384.34601 | I17: =-$E68*I$12 -> -392.41727
B18: Materials and consumables costs | C18: =INDEX('Income Statement - Data'!$C$3:$D$33,MATCH($B18,'Income Statement - Data'!$B$3:$B$33,0),MATCH('Profit & loss'!C$11,'Income Statement - Data'!$C$2:$D$2,0)) -> -104.4 | D18: =INDEX('Income Statement - Data'!$C$3:$D$33,MATCH($B18,'Income Statement - Data'!$B$3:$B$33,0),MATCH('Profit & loss'!D$11,'Income Statement - Data'!$C$2:$D$2,0)) -> -90 | E18: =-$E73*E$12 -> -93.227375 | F18: =-$E73*F$12 -> -95.184438 | G18: =-$E73*G$12 -> -97.088127 | H18: =-$E73*H$12 -> -99.02989 | I18: =-$E73*I$12 -> -101.10952
B19: Insurance premiums and accident claims | C19: =INDEX('Income Statement - Data'!$C$3:$D$33,MATCH($B19,'Income Statement - Data'!$B$3:$B$33,0),MATCH('Profit & loss'!C$11,'Income Statement - Data'!$C$2:$D$2,0)) -> -102.1 | D19: =INDEX('Income Statement - Data'!$C$3:$D$33,MATCH($B19,'Income Statement - Data'!$B$3:$B$33,0),MATCH('Profit & loss'!D$11,'Income Statement - Data'!$C$2:$D$2,0)) -> -122.6 | E19: =-$E78*E$12 -> -126.9964 | F19: =-$E78*F$12 -> -129.66236 | G19: =-$E78*G$12 -> -132.2556 | H19: =-$E78*H$12 -> -134.90072 | I19: =-$E78*I$12 -> -137.73363
B20: Premises costs | C20: =INDEX('Income Statement - Data'!$C$3:$D$33,MATCH($B20,'Income Statement - Data'!$B$3:$B$33,0),MATCH('Profit & loss'!C$11,'Income Statement - Data'!$C$2:$D$2,0)) -> -86.8 | D20: =INDEX('Income Statement - Data'!$C$3:$D$33,MATCH($B20,'Income Statement - Data'!$B$3:$B$33,0),MATCH('Profit & loss'!D$11,'Income Statement - Data'!$C$2:$D$2,0)) -> -97.5 | E20: =-$E$83*E$12*($D20/SUM($D$20:$D$28)) -> -100.99632 | F20: =-$E$83*F$12*($D20/SUM($D$20:$D$28)) -> -103.11647 | G20: =-$E$83*G$12*($D20/SUM($D$20:$D$28)) -> -105.1788 | H20: =-$E$83*H$12*($D20/SUM($D$20:$D$28)) -> -107.28238 | I20: =-$E$83*I$12*($D20/SUM($D$20:$D$28)) -> -109.53531
B21: Road tax and licence fees | C21: =INDEX('Income Statement - Data'!$C$3:$D$33,MATCH($B21,'Income Statement - Data'!$B$3:$B$33,0),MATCH('Profit & loss'!C$11,'Income Statement - Data'!$C$2:$D$2,0)) -> -74.6 | D21: =INDEX('Income Statement - Data'!$C$3:$D$33,MATCH($B21,'Income Statement - Data'!$B$3:$B$33,0),MATCH('Profit & loss'!D$11,'Income Statement - Data'!$C$2:$D$2,0)) -> -85.7 | E21: =-$E$83*E$12*($D21/SUM($D$20:$D$28)) -> -88.773178 | F21: =-$E$83*F$12*($D21/SUM($D$20:$D$28)) -> -90.636737 | G21: =-$E$83*G$12*($D21/SUM($D$20:$D$28)) -> -92.449472 | H21: =-$E$83*H$12*($D21/SUM($D$20:$D$28)) -> -94.298462 | I21: =-$E$83*I$12*($D21/SUM($D$20:$D$28)) -> -96.278729
B22: Utilities,It and communication costs | C22: =INDEX('Income Statement - Data'!$C$3:$D$33,MATCH($B22,'Income Statement - Data'!$B$3:$B$33,0),MATCH('Profit & loss'!C$11,'Income Statement - Data'!$C$2:$D$2,0)) -> -73.5 | D22: =INDEX('Income Statement - Data'!$C$3:$D$33,MATCH($B22,'Income Statement - Data'!$B$3:$B$33,0),MATCH('Profit & loss'!D$11,'Income Statement - Data'!$C$2:$D$2,0)) -> -90.6 | E22: =-$E$83*E$12*($D22/SUM($D$20:$D$28)) -> -93.848891 | F22: =-$E$83*F$12*($D22/SUM($D$20:$D$28)) -> -95.819001 | G22: =-$E$83*G$12*($D22/SUM($D$20:$D$28)) -> -97.735381 | H22: =-$E$83*H$12*($D22/SUM($D$20:$D$28)) -> -99.690089 | I22: =-$E$83*I$12*($D22/SUM($D$20:$D$28)) -> -101.78358
B23: Taxi drivers’ benefits | C23: =INDEX('Income Statement - Data'!$C$3:$D$33,MATCH($B23,'Income Statement - Data'!$B$3:$B$33,0),MATCH('Profit & loss'!C$11,'Income Statement - Data'!$C$2:$D$2,0)) -> -12 | D23: =INDEX('Income Statement - Data'!$C$3:$D$33,MATCH($B23,'Income Statement - Data'!$B$3:$B$33,0),MATCH('Profit & loss'!D$11,'Income Statement - Data'!$C$2:$D$2,0)) -> -70.4 | E23: =-$E$83*E$12*($D23/SUM($D$20:$D$28)) -> -72.924525 | F23: =-$E$83*F$12*($D23/SUM($D$20:$D$28)) -> -74.455383 | G23: =-$E$83*G$12*($D23/SUM($D$20:$D$28)) -> -75.944491 | H23: =-$E$83*H$12*($D23/SUM($D$20:$D$28)) -> -77.46338 | I23: =-$E$83*I$12*($D23/SUM($D$20:$D$28)) -> -79.090111
B24: Advertising production and promotion costs | C24: =INDEX('Income Statement - Data'!$C$3:$D$33,MATCH($B24,'Income Statement - Data'!$B$3:$B$33,0),MATCH('Profit & loss'!C$11,'Income Statement - Data'!$C$2:$D$2,0)) -> -34.5 | D24: =INDEX('Income Statement - Data'!$C$3:$D$33,MATCH($B24,'Income Statement - Data'!$B$3:$B$33,0),MATCH('Profit & loss'!D$11,'Income Statement - Data'!$C$2:$D$2,0)) -> -36 | E24: =-$E$83*E$12*($D24/SUM($D$20:$D$28)) -> -37.29095 | F24: =-$E$83*F$12*($D24/SUM($D$20:$D$28)) -> -38.073775 | G24: =-$E$83*G$12*($D24/SUM($D$20:$D$28)) -> -38.835251 | H24: =-$E$83*H$12*($D24/SUM($D$20:$D$28)) -> -39.611956 | I24: =-$E$83*I$12*($D24/SUM($D$20:$D$28)) -> -40.443807
B25: Professional fees | C25: =INDEX('Income Statement - Data'!$C$3:$D$33,MATCH($B25,'Income Statement - Data'!$B$3:$B$33,0),MATCH('Profit & loss'!C$11,'Income Statement - Data'!$C$2:$D$2,0)) -> -33.2 | D25: =INDEX('Income Statement - Data'!$C$3:$D$33,MATCH($B25,'Income Statement - Data'!$B$3:$B$33,0),MATCH('Profit & loss'!D$11,'Income Statement - Data'!$C$2:$D$2,0)) -> -30.8 | E25: =-$E$83*E$12*($D25/SUM($D$20:$D$28)) -> -31.90448 | F25: =-$E$83*F$12*($D25/SUM($D$20:$D$28)) -> -32.57423 | G25: =-$E$83*G$12*($D25/SUM($D$20:$D$28)) -> -33.225715 | H25: =-$E$83*H$12*($D25/SUM($D$20:$D$28)) -> -33.890229 | I25: =-$E$83*I$12*($D25/SUM($D$20:$D$28)) -> -34.601924
B26: Impairment of good will | C26: =INDEX('Income Statement - Data'!$C$3:$D$33,MATCH($B26,'Income Statement - Data'!$B$3:$B$33,0),MATCH('Profit & loss'!C$11,'Income Statement - Data'!$C$2:$D$2,0)) -> – | D26: =INDEX('Income Statement - Data'!$C$3:$D$33,MATCH($B26,'Income Statement - Data'!$B$3:$B$33,0),MATCH('Profit & loss'!D$11,'Income Statement - Data'!$C$2:$D$2,0)) -> -2.1 | E26: =-$E$83*E$12*($D26/SUM($D$20:$D$28)) -> -2.1753054 | F26: =-$E$83*F$12*($D26/SUM($D$20:$D$28)) -> -2.2209702 | G26: =-$E$83*G$12*($D26/SUM($D$20:$D$28)) -> -2.2653896 | H26: =-$E$83*H$12*($D26/SUM($D$20:$D$28)) -> -2.3106974 | I26: =-$E$83*I$12*($D26/SUM($D$20:$D$28)) -> -2.3592221
B27: Net gain on disposal of vehicles,premises and equipment | C27: =INDEX('Income Statement - Data'!$C$3:$D$33,MATCH($B27,'Income Statement - Data'!$B$3:$B$33,0),MATCH('Profit & loss'!C$11,'Income Statement - Data'!$C$2:$D$2,0)) -> 5.1 | D27: =INDEX('Income Statement - Data'!$C$3:$D$33,MATCH($B27,'Income Statement - Data'!$B$3:$B$33,0),MATCH('Profit & loss'!D$11,'Income Statement - Data'!$C$2:$D$2,0)) -> 25.9 | E27: 0 | F27: 0 | G27: 0 | H27: 0 | I27: 0
B28: Other operating costs | C28: =INDEX('Income Statement - Data'!$C$3:$D$33,MATCH($B28,'Income Statement - Data'!$B$3:$B$33,0),MATCH('Profit & loss'!C$11,'Income Statement - Data'!$C$2:$D$2,0)) -> -72.4 | D28: =INDEX('Income Statement - Data'!$C$3:$D$33,MATCH($B28,'Income Statement - Data'!$B$3:$B$33,0),MATCH('Profit & loss'!D$11,'Income Statement - Data'!$C$2:$D$2,0)) -> -69.7 | E28: =-$E$83*E$12*($D28/SUM($D$20:$D$28)) -> -72.199423 | F28: =-$E$83*F$12*($D28/SUM($D$20:$D$28)) -> -73.71506 | G28: =-$E$83*G$12*($D28/SUM($D$20:$D$28)) -> -75.189361 | H28: =-$E$83*H$12*($D28/SUM($D$20:$D$28)) -> -76.693148 | I28: =-$E$83*I$12*($D28/SUM($D$20:$D$28)) -> -78.303704
B29: Total operating costs | C29: =SUM(C14:C28) -> -3785.2 | D29: =SUM(D14:D28) -> -4286 | E29: =SUM(E14:E28) -> -4466.5235 | F29: =SUM(F14:F28) -> -4560.2864 | G29: =SUM(G14:G28) -> -4651.4922 | H29: =SUM(H14:H28) -> -4744.522 | I29: =SUM(I14:I28) -> -4844.157
B31: EBITDA | C31: =SUM(C12:C28) -> 691.3 | D31: =SUM(D12:D28) -> 772.6 | E31: =SUM(E12:E28) -> 773.47646 | F31: =SUM(F12:F28) -> 789.71356 | G31: =SUM(G12:G28) -> 805.50783 | H31: =SUM(H12:H28) -> 821.61798 | I31: =SUM(I12:I28) -> 838.87196
B32: Depreciation and amortisation | C32: =INDEX('Income Statement - Data'!$C$3:$D$33,MATCH($B32,'Income Statement - Data'!$B$3:$B$33,0),MATCH('Profit & loss'!C$11,'Income Statement - Data'!$C$2:$D$2,0)) -> -368.4 | D32: =INDEX('Income Statement - Data'!$C$3:$D$33,MATCH($B32,'Income Statement - Data'!$B$3:$B$33,0),MATCH('Profit & loss'!D$11,'Income Statement - Data'!$C$2:$D$2,0)) -> -399.6 | E32: ='Fixed assets schedule'!E14 -> -437.32044 | F32: ='Fixed assets schedule'!F14 -> -471.88961 | G32: ='Fixed assets schedule'!G14 -> -502.70317 | H32: ='Fixed assets schedule'!H14 -> -530.38301 | I32: ='Fixed assets schedule'!I14 -> -555.55293
B34: EBIT | C34: =SUM(C31:C32) -> 322.9 | D34: =SUM(D31:D32) -> 373 | E34: =SUM(E31:E32) -> 336.15601 | F34: =SUM(F31:F32) -> 317.82395 | G34: =SUM(G31:G32) -> 302.80466 | H34: =SUM(H31:H32) -> 291.23498 | I34: =SUM(I31:I32) -> 283.31904
B35: Other income/(costs)
B36: Investments income | C36: =INDEX('Income Statement - Data'!$C$3:$D$33,MATCH($B36,'Income Statement - Data'!$B$3:$B$33,0),MATCH('Profit & loss'!C$11,'Income Statement - Data'!$C$2:$D$2,0)) -> 31.7 | D36: =INDEX('Income Statement - Data'!$C$3:$D$33,MATCH($B36,'Income Statement - Data'!$B$3:$B$33,0),MATCH('Profit & loss'!D$11,'Income Statement - Data'!$C$2:$D$2,0)) -> 20.4 | E36: =E91*E$12 -> 21.131538 | F36: =F91*F$12 -> 21.575139 | G36: =G91*G$12 -> 22.006642 | H36: =H91*H$12 -> 22.446775 | I36: =I91*I$12 -> 22.918157
B37: Finance costs | C37: =INDEX('Income Statement - Data'!$C$3:$D$33,MATCH($B37,'Income Statement - Data'!$B$3:$B$33,0),MATCH('Profit & loss'!C$11,'Income Statement - Data'!$C$2:$D$2,0)) -> -38.9 | D37: =INDEX('Income Statement - Data'!$C$3:$D$33,MATCH($B37,'Income Statement - Data'!$B$3:$B$33,0),MATCH('Profit & loss'!D$11,'Income Statement - Data'!$C$2:$D$2,0)) -> -52.8 | E37: =-('debt schedule'!D7+'debt schedule'!D13) -> -70.480763 | F37: =-('debt schedule'!E7+'debt schedule'!E13) -> -70.480763 | G37: =-('debt schedule'!F7+'debt schedule'!F13) -> -70.480763 | H37: =-('debt schedule'!G7+'debt schedule'!G13) -> -70.480763 | I37: =-('debt schedule'!H7+'debt schedule'!H13) -> -70.480763
B38: Share of results of associates and joint ventures | C38: =INDEX('Income Statement - Data'!$C$3:$D$33,MATCH($B38,'Income Statement - Data'!$B$3:$B$33,0),MATCH('Profit & loss'!C$11,'Income Statement - Data'!$C$2:$D$2,0)) -> 1.8 | D38: =INDEX('Income Statement - Data'!$C$3:$D$33,MATCH($B38,'Income Statement - Data'!$B$3:$B$33,0),MATCH('Profit & loss'!D$11,'Income Statement - Data'!$C$2:$D$2,0)) -> 0.8 | E38: =E101*E$12 -> 0.82868778 | F38: =F101*F$12 -> 0.8460839 | G38: =G101*G$12 -> 0.86300557 | H38: =H101*H$12 -> 0.88026569 | I38: =I101*I$12 -> 0.89875127
B39: EBT | C39: =SUM(C34,C36:C38) -> 317.5 | D39: =SUM(D34,D36:D38) -> 341.4 | E39: =SUM(E34,E36:E38) -> 287.63547 | F39: =SUM(F34,F36:F38) -> 269.76441 | G39: =SUM(G34,G36:G38) -> 255.19354 | H39: =SUM(H34,H36:H38) -> 244.08125 | I39: =SUM(I34,I36:I38) -> 236.65518
B40: Taxation | C40: =INDEX('Income Statement - Data'!$C$3:$D$33,MATCH($B40,'Income Statement - Data'!$B$3:$B$33,0),MATCH('Profit & loss'!C$11,'Income Statement - Data'!$C$2:$D$2,0)) -> -61.8 | D40: =INDEX('Income Statement - Data'!$C$3:$D$33,MATCH($B40,'Income Statement - Data'!$B$3:$B$33,0),MATCH('Profit & loss'!D$11,'Income Statement - Data'!$C$2:$D$2,0)) -> -69.5 | E40: =-E39*E105 -> -57.270983 | F40: =-F39*F105 -> -53.712682 | G40: =-G39*G105 -> -50.811483 | H40: =-H39*H105 -> -48.59892 | I40: =-I39*I105 -> -47.120317
B41: Net income | C41: =SUM(C39:C40) -> 255.7 | D41: =SUM(D39:D40) -> 271.9 | E41: =SUM(E39:E40) -> 230.36449 | F41: =SUM(F39:F40) -> 216.05173 | G41: =SUM(G39:G40) -> 204.38206 | H41: =SUM(H39:H40) -> 195.48233 | I41: =SUM(I39:I40) -> 189.53486
B44: Scenario assumptions | C44: 2024 | D44: =D11 -> 2025 | E44: =E11 -> 2026 | F44: =F11 -> 2027 | G44: =G11 -> 2028 | H44: =H11 -> 2029 | I44: =I11 -> 2030 | J44: Base case
B45: Revenue growth | J45: variance
B46: selected case | D46: =OFFSET(D46,MATCH($C$9,$B47:$B49,0),) -> 0.13003463 | E46: =OFFSET(E46,MATCH($C$9,$B47:$B49,0),) -> 0.035859724 | F46: =OFFSET(F46,MATCH($C$9,$B47:$B49,0),) -> 0.020992366 | G46: =OFFSET(G46,MATCH($C$9,$B47:$B49,0),) -> 0.02 | H46: =OFFSET(H46,MATCH($C$9,$B47:$B49,0),) -> 0.02 | I46: =OFFSET(I46,MATCH($C$9,$B47:$B49,0),) -> 0.021
B47: Best case | D47: =(D$12-C$12)/C$12 -> 0.13003463 | E47: =E48+$J47 -> 0.045859724 | F47: =F48+$J47 -> 0.030992366 | G47: =G48+$J47 -> 0.03 | H47: =H48+$J47 -> 0.03 | I47: =I48+$J47 -> 0.031 | J47: 0.01
B48: Base case | D48: =(D$12-C$12)/C$12 -> 0.13003463 | E48: =(E$12-D$12)/D$12 -> 0.035859724 | F48: =(F$12-E$12)/E$12 -> 0.020992366 | G48: 0.02 | H48: 0.02 | I48: 0.021
B49: worst case | D49: =(D$12-C$12)/C$12 -> 0.13003463 | E49: =$E$48+$J49 -> 0.025859724 | F49: =F48+$J49 -> 0.010992366 | G49: =G48+$J49 -> 0.01 | H49: =H48+$J49 -> 0.01 | I49: =I48+$J49 -> 0.011 | J49: -0.01
B50: =B14 & " as % of revenue" -> Staff costs as % of revenue
B51: selected case | C51: =OFFSET(C51,MATCH($C$9,$B52:$B54,0),) -> 0.45216129 | D51: =OFFSET(D51,MATCH($C$9,$B52:$B54,0),) -> 0.44913612 | E51: =OFFSET(E51,MATCH($C$9,$B52:$B54,0),) -> 0.44913612 | F51: =OFFSET(F51,MATCH($C$9,$B52:$B54,0),) -> 0.44913612 | G51: =OFFSET(G51,MATCH($C$9,$B52:$B54,0),) -> 0.44913612 | H51: =OFFSET(H51,MATCH($C$9,$B52:$B54,0),) -> 0.44913612 | I51: =OFFSET(I51,MATCH($C$9,$B52:$B54,0),) -> 0.44913612
B52: Best case | C52: =-C$14/C$12 -> 0.45216129 | D52: =-D$14/D$12 -> 0.44913612 | E52: =$E$53+$J52 -> 0.43913612 | F52: =$E$53+$J52 -> 0.43913612 | G52: =$E$53+$J52 -> 0.43913612 | H52: =$E$53+$J52 -> 0.43913612 | I52: =$E$53+$J52 -> 0.43913612 | J52: -0.01
B53: Base case | C53: =-C$14/C$12 -> 0.45216129 | D53: =-$D$14/$D$12 -> 0.44913612 | E53: =-$D$14/$D$12 -> 0.44913612 | F53: =-$D$14/$D$12 -> 0.44913612 | G53: =-$D$14/$D$12 -> 0.44913612 | H53: =-$D$14/$D$12 -> 0.44913612 | I53: =-$D$14/$D$12 -> 0.44913612
B54: worst case | C54: =-C$14/C$12 -> 0.45216129 | D54: =-D$14/D$12 -> 0.44913612 | E54: =E$53+$J54 -> 0.45913612 | F54: =F$53+$J54 -> 0.45913612 | G54: =G$53+$J54 -> 0.45913612 | H54: =H$53+$J54 -> 0.45913612 | I54: =I$53+$J54 -> 0.45913612 | J54: 0.01
B55: =B15 & " as % of revenue" -> Contract services and subcontractor costs as % of revenue
B56: selected case | C56: =OFFSET(C56,MATCH($C$9,$B57:$B59,0),) -> 0.099586731 | D56: =OFFSET(D56,MATCH($C$9,$B57:$B59,0),) -> 0.12736726 | E56: =OFFSET(E56,MATCH($C$9,$B57:$B59,0),) -> 0.12736726 | F56: =OFFSET(F56,MATCH($C$9,$B57:$B59,0),) -> 0.12736726 | G56: =OFFSET(G56,MATCH($C$9,$B57:$B59,0),) -> 0.12736726 | H56: =OFFSET(H56,MATCH($C$9,$B57:$B59,0),) -> 0.12736726 | I56: =OFFSET(I56,MATCH($C$9,$B57:$B59,0),) -> 0.12736726
B57: Best case | C57: =-C$15/C$12 -> 0.099586731 | D57: =-$D$15/$D$12 -> 0.12736726 | E57: =E$58+$J57 -> 0.11736726 | F57: =F$58+$J57 -> 0.11736726 | G57: =G$58+$J57 -> 0.11736726 | H57: =H$58+$J57 -> 0.11736726 | I57: =I$58+$J57 -> 0.11736726 | J57: -0.01
B58: Base case | C58: =-C$15/C$12 -> 0.099586731 | D58: =-$D$15/$D$12 -> 0.12736726 | E58: =-$D$15/$D$12 -> 0.12736726 | F58: =-$D$15/$D$12 -> 0.12736726 | G58: =-$D$15/$D$12 -> 0.12736726 | H58: =-$D$15/$D$12 -> 0.12736726 | I58: =-$D$15/$D$12 -> 0.12736726
B59: worst case | C59: =-C$15/C$12 -> 0.099586731 | D59: =-D$15/D$12 -> 0.12736726 | E59: =E$58+$J59 -> 0.13736726 | F59: =F$58+$J59 -> 0.13736726 | G59: =G$58+$J59 -> 0.13736726 | H59: =H$58+$J59 -> 0.13736726 | I59: =I$58+$J59 -> 0.13736726 | J59: 0.01
B60: =B16 & " as % of revenue" -> Fuel and electricity costs as % of revenue
B61: selected case | C61: =OFFSET(C61,MATCH($C$9,$B62:$B64,0),) -> 0.088730035 | D61: =OFFSET(D61,MATCH($C$9,$B62:$B64,0),) -> 0.069367019 | E61: =OFFSET(E61,MATCH($C$9,$B62:$B64,0),) -> 0.069367019 | F61: =OFFSET(F61,MATCH($C$9,$B62:$B64,0),) -> 0.069367019 | G61: =OFFSET(G61,MATCH($C$9,$B62:$B64,0),) -> 0.069367019 | H61: =OFFSET(H61,MATCH($C$9,$B62:$B64,0),) -> 0.069367019 | I61: =OFFSET(I61,MATCH($C$9,$B62:$B64,0),) -> 0.069367019
B62: Best case | C62: =-C$16/C$12 -> 0.088730035 | D62: =-D$16/D$12 -> 0.069367019 | E62: =E$63+$J62 -> 0.059367019 | F62: =F$63+$J62 -> 0.059367019 | G62: =G$63+$J62 -> 0.059367019 | H62: =H$63+$J62 -> 0.059367019 | I62: =I$63+$J62 -> 0.059367019 | J62: -0.01
B63: Base case | C63: =-C$16/C$12 -> 0.088730035 | D63: =-$D$16/$D$12 -> 0.069367019 | E63: =-$D$16/$D$12 -> 0.069367019 | F63: =-$D$16/$D$12 -> 0.069367019 | G63: =-$D$16/$D$12 -> 0.069367019 | H63: =-$D$16/$D$12 -> 0.069367019 | I63: =-$D$16/$D$12 -> 0.069367019
B64: worst case | C64: =-C$16/C$12 -> 0.088730035 | D64: =-D$16/D$12 -> 0.069367019 | E64: =E$63+$J64 -> 0.079367019 | F64: =F$63+$J64 -> 0.079367019 | G64: =G$63+$J64 -> 0.079367019 | H64: =H$63+$J64 -> 0.079367019 | I64: =I$63+$J64 -> 0.079367019 | J64: 0.01
B65: =B17 & " as % of revenue" -> Repairs and maintenance costs as % of revenue
B66: selected case | C66: =OFFSET(C66,MATCH($C$9,$B67:$B69,0),) -> 0.07365129 | D66: =OFFSET(D66,MATCH($C$9,$B67:$B69,0),) -> 0.069050725 | E66: =OFFSET(E66,MATCH($C$9,$B67:$B69,0),) -> 0.069050725 | F66: =OFFSET(F66,MATCH($C$9,$B67:$B69,0),) -> 0.069050725 | G66: =OFFSET(G66,MATCH($C$9,$B67:$B69,0),) -> 0.069050725 | H66: =OFFSET(H66,MATCH($C$9,$B67:$B69,0),) -> 0.069050725 | I66: =OFFSET(I66,MATCH($C$9,$B67:$B69,0),) -> 0.069050725
B67: Best case | C67: =-C$17/C$12 -> 0.07365129 | D67: =-D$17/D$12 -> 0.069050725 | E67: =E$68+$J67 -> 0.059050725 | F67: =F$68+$J67 -> 0.059050725 | G67: =G$68+$J67 -> 0.059050725 | H67: =H$68+$J67 -> 0.059050725 | I67: =I$68+$J67 -> 0.059050725 | J67: -0.01
B68: Base case | C68: =-C$17/C$12 -> 0.07365129 | D68: =-D$17/D$12 -> 0.069050725 | E68: =-E$17/E$12 -> 0.069050725 | F68: =-F$17/F$12 -> 0.069050725 | G68: =-G$17/G$12 -> 0.069050725 | H68: =-H$17/H$12 -> 0.069050725 | I68: =-I$17/I$12 -> 0.069050725
B69: worst case | C69: =-C$17/C$12 -> 0.07365129 | D69: =-D$17/D$12 -> 0.069050725 | E69: =E$68+$J69 -> 0.079050725 | F69: =F$68+$J69 -> 0.079050725 | G69: =G$68+$J69 -> 0.079050725 | H69: =H$68+$J69 -> 0.079050725 | I69: =I$68+$J69 -> 0.079050725 | J69: 0.01
B70: =B18 & " as % of revenue" -> Materials and consumables costs as % of revenue
B71: selected case | C71: =OFFSET(C71,MATCH($C$9,$B72:$B74,0),) -> 0.023321792 | D71: =OFFSET(D71,MATCH($C$9,$B72:$B74,0),) -> 0.017791484 | E71: =OFFSET(E71,MATCH($C$9,$B72:$B74,0),) -> 0.017791484 | F71: =OFFSET(F71,MATCH($C$9,$B72:$B74,0),) -> 0.017791484 | G71: =OFFSET(G71,MATCH($C$9,$B72:$B74,0),) -> 0.017791484 | H71: =OFFSET(H71,MATCH($C$9,$B72:$B74,0),) -> 0.017791484 | I71: =OFFSET(I71,MATCH($C$9,$B72:$B74,0),) -> 0.017791484
B72: Best case | C72: =-C$18/$C$12 -> 0.023321792 | D72: =-D$18/$C$12 -> 0.020104993 | E72: =E$73+$J72 -> 0.0077914838 | F72: =F$73+$J72 -> 0.0077914838 | G72: =G$73+$J72 -> 0.0077914838 | H72: =H$73+$J72 -> 0.0077914838 | I72: =I$73+$J72 -> 0.0077914838 | J72: -0.01
B73: Base case | C73: =-C$18/$C$12 -> 0.023321792 | D73: =-$D$18/$D$12 -> 0.017791484 | E73: =-$D$18/$D$12 -> 0.017791484 | F73: =-$D$18/$D$12 -> 0.017791484 | G73: =-$D$18/$D$12 -> 0.017791484 | H73: =-$D$18/$D$12 -> 0.017791484 | I73: =-$D$18/$D$12 -> 0.017791484
B74: worst case | C74: =-C$18/$C$12 -> 0.023321792 | D74: =-D$18/$C$12 -> 0.020104993 | E74: =E$73+$J74 -> 0.027791484 | F74: =F$73+$J74 -> 0.027791484 | G74: =G$73+$J74 -> 0.027791484 | H74: =H$73+$J74 -> 0.027791484 | I74: =I$73+$J74 -> 0.027791484 | J74: 0.01
B75: =B19 & " as % of revenue" -> Insurance premiums and accident claims as % of revenue
B76: selected case | C76: =OFFSET(C76,MATCH($C$9,$B77:$B79,0),) -> 0.022807997 | D76: =OFFSET(D76,MATCH($C$9,$B77:$B79,0),) -> 0.024235955 | E76: =OFFSET(E76,MATCH($C$9,$B77:$B79,0),) -> 0.024235955 | F76: =OFFSET(F76,MATCH($C$9,$B77:$B79,0),) -> 0.024235955 | G76: =OFFSET(G76,MATCH($C$9,$B77:$B79,0),) -> 0.024235955 | H76: =OFFSET(H76,MATCH($C$9,$B77:$B79,0),) -> 0.024235955 | I76: =OFFSET(I76,MATCH($C$9,$B77:$B79,0),) -> 0.024235955
B77: Best case | C77: =-C$19/C$12 -> 0.022807997 | D77: =-D$19/D$12 -> 0.024235955 | E77: =E$78+$J77 -> 0.014235955 | F77: =F$78+$J77 -> 0.014235955 | G77: =G$78+$J77 -> 0.014235955 | H77: =H$78+$J77 -> 0.014235955 | I77: =I$78+$J77 -> 0.014235955 | J77: -0.01
B78: Base case | C78: =-C$19/C$12 -> 0.022807997 | D78: =-D$19/D$12 -> 0.024235955 | E78: =-E$19/E$12 -> 0.024235955 | F78: =-F$19/F$12 -> 0.024235955 | G78: =-G$19/G$12 -> 0.024235955 | H78: =-H$19/H$12 -> 0.024235955 | I78: =-I$19/I$12 -> 0.024235955
B79: worst case | C79: =-C$19/C$12 -> 0.022807997 | D79: =-D$19/D$12 -> 0.024235955 | E79: =E$78+$J79 -> 0.034235955 | F79: =F$78+$J79 -> 0.034235955 | G79: =G$78+$J79 -> 0.034235955 | H79: =H$78+$J79 -> 0.034235955 | I79: =I$78+$J79 -> 0.034235955 | J79: 0.01
B80: ="general operating costs" & " as % of revenue" -> general operating costs as % of revenue
B81: selected case | C81: =OFFSET(C81,MATCH($C$9,$B82:$B84,0),) -> 0.085312186 | D81: =OFFSET(D81,MATCH($C$9,$B82:$B84,0),) -> 0.090321433 | E81: =OFFSET(E81,MATCH($C$9,$B82:$B84,0),) -> 0.090321433 | F81: =OFFSET(F81,MATCH($C$9,$B82:$B84,0),) -> 0.090321433 | G81: =OFFSET(G81,MATCH($C$9,$B82:$B84,0),) -> 0.090321433 | H81: =OFFSET(H81,MATCH($C$9,$B82:$B84,0),) -> 0.090321433 | I81: =OFFSET(I81,MATCH($C$9,$B82:$B84,0),) -> 0.090321433
B82: Best case | C82: =-SUM(C$20:C$28)/C$12 -> 0.085312186 | D82: =-SUM(D$20:D$28)/D$12 -> 0.090321433 | E82: =E$83+$J82 -> 0.080321433 | F82: =F$83+$J82 -> 0.080321433 | G82: =G$83+$J82 -> 0.080321433 | H82: =H$83+$J82 -> 0.080321433 | I82: =I$83+$J82 -> 0.080321433 | J82: -0.01
B83: Base case | C83: =-SUM(C$20:C$28)/C$12 -> 0.085312186 | D83: =-SUM($D$20:$D$28)/$D$12 -> 0.090321433 | E83: =-SUM($D$20:$D$28)/$D$12 -> 0.090321433 | F83: =-SUM($D$20:$D$28)/$D$12 -> 0.090321433 | G83: =-SUM($D$20:$D$28)/$D$12 -> 0.090321433 | H83: =-SUM($D$20:$D$28)/$D$12 -> 0.090321433 | I83: =-SUM($D$20:$D$28)/$D$12 -> 0.090321433
B84: worst case | C84: =-SUM(C$20:C$28)/C$12 -> 0.085312186 | D84: =-SUM(D$20:D$28)/D$12 -> 0.090321433 | E84: =E$83+$J84 -> 0.10032143 | F84: =F$83+$J84 -> 0.10032143 | G84: =G$83+$J84 -> 0.10032143 | H84: =H$83+$J84 -> 0.10032143 | I84: =I$83+$J84 -> 0.10032143 | J84: 0.01
B85: =B32 & " as % of revenue" -> Depreciation and amortisation as % of revenue
B86: selected case | C86: =OFFSET(C86,MATCH($C$9,$B87:$B89,0),) -> 0.082296437 | D86: =OFFSET(D86,MATCH($C$9,$B87:$B89,0),) -> 0.078994188 | E86: =OFFSET(E86,MATCH($C$9,$B87:$B89,0),) -> 0.0834581 | F86: =OFFSET(F86,MATCH($C$9,$B87:$B89,0),) -> 0.088203665 | G86: =OFFSET(G86,MATCH($C$9,$B87:$B89,0),) -> 0.092120793 | H86: =OFFSET(H86,MATCH($C$9,$B87:$B89,0),) -> 0.0952874 | I86: =OFFSET(I86,MATCH($C$9,$B87:$B89,0),) -> 0.097756484
B87: Best case | C87: =-C$32/$C$12 -> 0.082296437 | D87: =-D$32/D$12 -> 0.078994188 | E87: =E$88+$J87 -> 0.0734581 | F87: =F$88+$J87 -> 0.078203665 | G87: =G$88+$J87 -> 0.082120793 | H87: =H$88+$J87 -> 0.0852874 | I87: =I$88+$J87 -> 0.087756484 | J87: -0.01
B88: Base case | C88: =-C$32/C$12 -> 0.082296437 | D88: =-D$32/D$12 -> 0.078994188 | E88: =-E$32/E$12 -> 0.0834581 | F88: =-F$32/F$12 -> 0.088203665 | G88: =-G$32/G$12 -> 0.092120793 | H88: =-H$32/H$12 -> 0.0952874 | I88: =-I$32/I$12 -> 0.097756484
B89: worst case | C89: =-C$32/$C$12 -> 0.082296437 | D89: =-D$32/D$12 -> 0.078994188 | E89: =E$88+$J89 -> 0.0934581 | F89: =F$88+$J89 -> 0.098203665 | G89: =G$88+$J89 -> 0.10212079 | H89: =H$88+$J89 -> 0.1052874 | I89: =I$88+$J89 -> 0.10775648 | J89: 0.01
B90: =B36 & " as % of revenue" -> Investments income as % of revenue
B91: selected case | C91: =OFFSET(C$91,MATCH($C$9,$B92:$B94,0),0) -> 0.0070814252 | D91: =OFFSET(D$91,MATCH($C$9,$B92:$B94,0),0) -> 0.0040327363 | E91: =OFFSET(E$91,MATCH($C$9,$B92:$B94,0),0) -> 0.0040327363 | F91: =OFFSET(F$91,MATCH($C$9,$B92:$B94,0),0) -> 0.0040327363 | G91: =OFFSET(G$91,MATCH($C$9,$B92:$B94,0),0) -> 0.0040327363 | H91: =OFFSET(H$91,MATCH($C$9,$B92:$B94,0),0) -> 0.0040327363 | I91: =OFFSET(I$91,MATCH($C$9,$B92:$B94,0),0) -> 0.0040327363
B92: Best case | C92: =C$36/C$12 -> 0.0070814252 | D92: =D$36/D$12 -> 0.0040327363 | E92: =E93+$J$92 -> 0.0060327363 | F92: =F93+$J$92 -> 0.0060327363 | G92: =G93+$J$92 -> 0.0060327363 | H92: =H93+$J$92 -> 0.0060327363 | I92: =I93+$J$92 -> 0.0060327363 | J92: 0.002
B93: Base case | C93: =C$36/C$12 -> 0.0070814252 | D93: =$D$36/$D$12 -> 0.0040327363 | E93: =$D$36/$D$12 -> 0.0040327363 | F93: =$D$36/$D$12 -> 0.0040327363 | G93: =$D$36/$D$12 -> 0.0040327363 | H93: =$D$36/$D$12 -> 0.0040327363 | I93: =$D$36/$D$12 -> 0.0040327363
B94: worst case | C94: =C$36/C$12 -> 0.0070814252 | D94: =D$36/D$12 -> 0.0040327363 | E94: =E$93+$J94 -> 0.0020327363 | F94: =F$93+$J94 -> 0.0020327363 | G94: =G$93+$J94 -> 0.0020327363 | H94: =H$93+$J94 -> 0.0020327363 | I94: =I$93+$J94 -> 0.0020327363 | J94: -0.002
B95: =B37 & " as % of revenue" -> Finance costs as % of revenue
B96: selected case | C96: =OFFSET(C$96,MATCH($C$9,$B97:$B99,0),0) -> 0.0086898246 | D96: =OFFSET(D$96,MATCH($C$9,$B97:$B99,0),0) -> 0.010437671 | E96: =OFFSET(E$96,MATCH($C$9,$B97:$B99,0),0) -> 0.010437671 | F96: =OFFSET(F$96,MATCH($C$9,$B97:$B99,0),0) -> 0.010437671 | G96: =OFFSET(G$96,MATCH($C$9,$B97:$B99,0),0) -> 0.010437671 | H96: =OFFSET(H$96,MATCH($C$9,$B97:$B99,0),0) -> 0.010437671 | I96: =OFFSET(I$96,MATCH($C$9,$B97:$B99,0),0) -> 0.010437671
B97: Best case | C97: =-C$37/C$12 -> 0.0086898246 | D97: =-D$37/D$12 -> 0.010437671 | E97: =E98+$J$97 -> 0.0084376705 | F97: =F98+$J$97 -> 0.0084376705 | G97: =G98+$J$97 -> 0.0084376705 | H97: =H98+$J$97 -> 0.0084376705 | I97: =I98+$J$97 -> 0.0084376705 | J97: -0.002
B98: Base case | C98: =-C$37/C$12 -> 0.0086898246 | D98: =-$D$37/$D$12 -> 0.010437671 | E98: =-$D$37/$D$12 -> 0.010437671 | F98: =-$D$37/$D$12 -> 0.010437671 | G98: =-$D$37/$D$12 -> 0.010437671 | H98: =-$D$37/$D$12 -> 0.010437671 | I98: =-$D$37/$D$12 -> 0.010437671
B99: worst case | C99: =-C$37/C$12 -> 0.0086898246 | D99: =-D$37/D$12 -> 0.010437671 | E99: =$E98+$J$99 -> 0.012437671 | F99: =$E98+$J$99 -> 0.012437671 | G99: =$E98+$J$99 -> 0.012437671 | H99: =$E98+$J$99 -> 0.012437671 | I99: =$E98+$J$99 -> 0.012437671 | J99: 0.002
B100: =B38 & " as % of revenue" -> Share of results of associates and joint ventures as % of revenue
B101: selected case | C101: =OFFSET(C$101,MATCH($C$9,$B102:$B104,0),0) -> 0.00040209985 | D101: =OFFSET(D$101,MATCH($C$9,$B102:$B104,0),0) -> 0.00015814652 | E101: =OFFSET(E$101,MATCH($C$9,$B102:$B104,0),0) -> 0.00015814652 | F101: =OFFSET(F$101,MATCH($C$9,$B102:$B104,0),0) -> 0.00015814652 | G101: =OFFSET(G$101,MATCH($C$9,$B102:$B104,0),0) -> 0.00015814652 | H101: =OFFSET(H$101,MATCH($C$9,$B102:$B104,0),0) -> 0.00015814652 | I101: =OFFSET(I$101,MATCH($C$9,$B102:$B104,0),0) -> 0.00015814652
B102: Best case | C102: =C$38/C$12 -> 0.00040209985 | D102: =D$38/D$12 -> 0.00015814652 | E102: =E103+$J102 -> 0.00035814652 | F102: =F103+$J102 -> 0.00035814652 | G102: =G103+$J102 -> 0.00035814652 | H102: =H103+$J102 -> 0.00035814652 | I102: =I103+$J102 -> 0.00035814652 | J102: 0.0002
B103: Base case | C103: =C$38/C$12 -> 0.00040209985 | D103: =$D38/$D$12 -> 0.00015814652 | E103: =$D38/$D$12 -> 0.00015814652 | F103: =$D38/$D$12 -> 0.00015814652 | G103: =$D38/$D$12 -> 0.00015814652 | H103: =$D38/$D$12 -> 0.00015814652 | I103: =$D38/$D$12 -> 0.00015814652
B104: worst case | C104: =C$38/C$12 -> 0.00040209985 | D104: =D$38/D$12 -> 0.00015814652 | E104: =E$103+$J104 -> -4.1853477e-05 | F104: =F$103+$J104 -> -4.1853477e-05 | G104: =G$103+$J104 -> -4.1853477e-05 | H104: =H$103+$J104 -> -4.1853477e-05 | I104: =I$103+$J104 -> -4.1853477e-05 | J104: -0.0002
B105: =B40 & " as % of EBT" -> Taxation as % of EBT | C105: =-C40/C39 -> 0.19464567 | D105: =-D40/D39 -> 0.20357352 | E105: =AVERAGE(C105,D105) -> 0.1991096 | F105: 0.1991096 | G105: 0.1991096 | H105: 0.1991096 | I105: 0.1991096

Sheet cash Flow
B2: Cash Flow Statement | E2: Forecast
B3: $ in millions | C3: 2024 | D3: =C3+1 -> 2025 | E3: =D3+1 -> 2026 | F3: =E3+1 -> 2027 | G3: =F3+1 -> 2028 | H3: =G3+1 -> 2029 | I3: =H3+1 -> 2030
B4: Profit before Taxation | C4: 317.5 | D4: 341.4 | E4: ='Profit & loss'!E39 -> 287.63547 | F4: ='Profit & loss'!F39 -> 269.76441 | G4: ='Profit & loss'!G39 -> 255.19354 | H4: ='Profit & loss'!H39 -> 244.08125 | I4: ='Profit & loss'!I39 -> 236.65518
B5: Depreciation and amortisation | C5: 368.4 | D5: 399.6 | E5: =-'Profit & loss'!E32 -> 437.32044 | F5: =-'Profit & loss'!F32 -> 471.88961 | G5: =-'Profit & loss'!G32 -> 502.70317 | H5: =-'Profit & loss'!H32 -> 530.38301 | I5: =-'Profit & loss'!I32 -> 555.55293
B6: Finance costs | C6: 38.9 | D6: 52.8 | E6: =-'Profit & loss'!E37 -> 70.480763 | F6: =-'Profit & loss'!F37 -> 70.480763 | G6: =-'Profit & loss'!G37 -> 70.480763 | H6: =-'Profit & loss'!H37 -> 70.480763 | I6: =-'Profit & loss'!I37 -> 70.480763
B7: Dividend income | C7: -6.1 | D7: 0 | E7: 0 | F7: 0 | G7: 0 | H7: 0 | I7: 0
B8: Interest income | C8: -25.1 | D8: -18.9 | G8: 0 | H8: 0 | I8: 0
B9: Net gain on disposal of vehicles,premises and equipment | C9: -5.1 | D9: -0.3 | E9: 0 | F9: 0 | G9: 0 | H9: 0 | I9: 0
B10: Net gain on disposal of assets held for sale | C10: – | D10: -25.6 | E10: 0 | F10: 0 | G10: 0 | H10: 0 | I10: 0
B11: Net gain on disposal of subsidiaries | C11: – | D11: -1.1 | E11: 0 | F11: 0 | G11: 0 | H11: 0 | I11: 0
B12: Net gain on disposal of investments | C12: -0.4 | D12: – | E12: 0 | F12: 0 | G12: 0 | H12: 0 | I12: 0
B13: Impairment of goodwill | C13: – | D13: 2.1 | E13: 0 | F13: 0 | G13: 0 | H13: 0 | I13: 0
B14: Provision for accident claims | C14: 10.6 | D14: 33.4 | E14: =-E23 -> 28.7 | F14: =-F23 -> 21.3 | G14: =-G23 -> 21.3 | H14: =-H23 -> 21.3 | I14: =-I23 -> 21.3
B15: Allowance for inventory obsolescence | C15: 7.8 | D15: 6.1 | E15: 0 | F15: 0 | G15: 0 | H15: 0 | I15: 0
B16: Allowance for/(reversal of) expected credit losses | C16: -0.7 | D16: 0.4 | E16: 0 | F16: 0 | G16: 0 | H16: 0 | I16: 0
B17: ="change in " & "Inventories" -> change in Inventories | C17: -22 | D17: 0.8 | E17: =-('balance sheet'!I9-'balance sheet'!H9) -> -5.4255762 | F17: =-('balance sheet'!J9-'balance sheet'!I9) -> -3.2900407 | G17: =-('balance sheet'!K9-'balance sheet'!J9) -> -3.2003123 | H17: =-('balance sheet'!L9-'balance sheet'!K9) -> -3.2643186 | I17: =-('balance sheet'!M9-'balance sheet'!L9) -> -3.4960852
B18: ="change in " & "Trade, other receivables and prepayments" -> change in Trade, other receivables and prepayments | C18: -34.9 | D18: -48.3 | E18: =-(SUM('balance sheet'!I7,'balance sheet'!I8)-SUM('balance sheet'!H7,'balance sheet'!H8)) -> -31.022247 | F18: =-(SUM('balance sheet'!J7,'balance sheet'!J8)-SUM('balance sheet'!I7,'balance sheet'!I8)) -> -18.811727 | G18: =-(SUM('balance sheet'!K7,'balance sheet'!K8)-SUM('balance sheet'!J7,'balance sheet'!J8)) -> -18.298679 | H18: =-(SUM('balance sheet'!L7,'balance sheet'!L8)-SUM('balance sheet'!K7,'balance sheet'!K8)) -> -18.664653 | I18: =-(SUM('balance sheet'!M7,'balance sheet'!M8)-SUM('balance sheet'!L7,'balance sheet'!L8)) -> -19.989843
B19: ="change in " & "Service concession receivables,net of deferred grants" -> change in Service concession receivables,net of deferred grants | C19: 0.1 | D19: -133.6 | E19: 0 | F19: 0 | G19: 0 | H19: 0 | I19: 0
B20: ="change in " & "Trade and other payables" -> change in Trade and other payables | C20: 4.2 | D20: -76.9 | E20: ='balance sheet'!I30-'balance sheet'!H30 -> 34.217349 | F20: ='balance sheet'!J30-'balance sheet'!I30 -> 20.749219 | G20: ='balance sheet'!K30-'balance sheet'!J30 -> 20.183331 | H20: ='balance sheet'!L30-'balance sheet'!K30 -> 20.586998 | I20: ='balance sheet'!M30-'balance sheet'!L30 -> 22.048675
B21: ="change in " & "Other liabilities" -> change in Other liabilities | C21: -12.9 | D21: 31.6 | E21: ='balance sheet'!I43-'balance sheet'!H43 -> 0 | F21: ='balance sheet'!J43-'balance sheet'!I43 -> 0 | G21: ='balance sheet'!K43-'balance sheet'!J43 -> 0 | H21: ='balance sheet'!L43-'balance sheet'!K43 -> 0 | I21: ='balance sheet'!M43-'balance sheet'!L43 -> 0
B22: Payments of service benefits and long service awards | C22: -1.6 | D22: -1 | E22: -1 | F22: -1 | G22: -1 | H22: -1 | I22: -1
B23: Payments of accident claims | C23: -19.5 | D23: -28.7 | E23: -28.7 | F23: -21.3 | G23: -21.3 | H23: -21.3 | I23: -21.3
B24: Income tax paid | C24: -65.9 | D24: -73.8 | E24: ='Profit & loss'!E40 -> -57.270983 | F24: ='Profit & loss'!F40 -> -53.712682 | G24: ='Profit & loss'!G40 -> -50.811483 | H24: ='Profit & loss'!H40 -> -48.59892 | I24: ='Profit & loss'!I40 -> -47.120317
B25: Interest paid arising from leases | C25: -6.9 | D25: -10 | E25: =-'debt schedule'!D13 -> -10.592967 | F25: =-'debt schedule'!E13 -> -10.592967 | G25: =-'debt schedule'!F13 -> -10.592967 | H25: =-'debt schedule'!G13 -> -10.592967 | I25: =-'debt schedule'!H13 -> -10.592967
B26: Others | C26: 0.7 | D26: 1.7 | E26: 0 | F26: 0 | G26: 0 | H26: 0 | I26: 0
B27: Operating Cash Flow | C27: =SUM(C4:C26) -> 547.1 | D27: =SUM(D4:D26) -> 451.7 | E27: =SUM(E4:E26) -> 724.34226 | F27: =SUM(F4:F26) -> 745.47658 | G27: =SUM(G4:G26) -> 764.65737 | H27: =SUM(H4:H26) -> 783.41117 | I27: =SUM(I4:I26) -> 802.53833
B29: Purchases of vehicles, premises and equipment | C29: -445.1 | D29: -565.4 | E29: 0 | F29: 0 | G29: 0 | H29: 0 | I29: 0
B30: Less: Proceeds from disposal of vehicles, premises and equipment | C30: 72.1 | D30: 55.1 | E30: 0 | F30: 0 | G30: 0 | H30: 0 | I30: 0
B31: Cash payments on purchase of vehicles, premises and equipment | C31: -373 | D31: -510.3 | E31: 0 | F31: 0 | G31: 0 | H31: 0 | I31: 0
B32: Proceeds from disposal of asset held for sale | C32: – | D32: 54.5 | E32: 0 | F32: 0 | G32: 0 | H32: 0 | I32: 0
B33: Proceeds from disposal of subsidiaries | C33: – | D33: 4.7 | E33: 0 | F33: 0 | G33: 0 | H33: 0 | I33: 0
B34: Proceeds from disposal of investments | C34: – | D34: 3.2 | E34: 0 | F34: 0 | G34: 0 | H34: 0 | I34: 0
B35: Investments made | C35: -0.4 | D35: -2 | E35: 0 | F35: 0 | G35: 0 | H35: 0 | I35: 0
B36: Additions to intangible assets | C36: -23.9 | D36: -22.4 | E36: 0 | F36: 0 | G36: 0 | H36: 0 | I36: 0
B37: Acquisition of business/ subsidiaries, net of cash | C37: -604.5 | D37: -49 | E37: 0 | F37: 0 | G37: 0 | H37: 0 | I37: 0
B38: Increase in investment in associates and joint ventures | C38: -0.7 | D38: -0.8 | E38: 0 | F38: 0 | G38: 0 | H38: 0 | I38: 0
B39: Interest received | C39: 24.9 | D39: 19.5 | E39: 0 | F39: 0 | G39: 0 | H39: 0 | I39: 0
B40: Dividend received from associate/ investments | C40: 7.5 | D40: 0.1 | E40: 0 | F40: 0 | G40: 0 | H40: 0 | I40: 0
B41: capital expenditures | E41: =-'Fixed assets schedule'!E4 -> -604.21698 | F41: =-'Fixed assets schedule'!F4 -> -616.90092 | G41: =-'Fixed assets schedule'!G4 -> -629.23894 | H41: =-'Fixed assets schedule'!H4 -> -641.82372 | I41: =-'Fixed assets schedule'!I4 -> -655.30202
B43: Investing Cash Flow | C43: =SUM(C31:C42) -> -970.1 | D43: =SUM(D31:D42) -> -502.5 | E43: =SUM(E31:E42) -> -604.21698 | F43: =SUM(F31:F42) -> -616.90092 | G43: =SUM(G31:G42) -> -629.23894 | H43: =SUM(H31:H42) -> -641.82372 | I43: =SUM(I31:I42) -> -655.30202
B45: New loans raised | C45: 3219 | D45: 3747.2 | E45: 0 | F45: 0 | G45: 0 | H45: 0 | I45: 0
B46: Repayment of borrowings and lease liabilities from financial institutions | C46: -2496.8 | D46: -3269.7 | E46: 0 | F46: 0 | G46: 0 | H46: 0 | I46: 0
B47: Repayment of lease liabilities | C47: -42.6 | D47: -61.9 | E47: 0 | F47: 0 | G47: 0 | H47: 0 | I47: 0
B48: Acquisition of non-controlling interests | C48: – | D48: -119.2 | E48: 0 | F48: 0 | G48: 0 | H48: 0 | I48: 0
B49: Capital contribution from non-controlling shareholder of a subsidiary | C49: – | D49: 3.3 | E49: 0 | F49: 0 | G49: 0 | H49: 0 | I49: 0
B50: Dividends paid to shareholders of the Company | C50: -157.7 | D50: -176.8 | E50: ='retained earnings schedule'!D11 -> -149.79199 | F50: ='retained earnings schedule'!E11 -> -140.48527 | G50: ='retained earnings schedule'!F11 -> -132.8972 | H50: ='retained earnings schedule'!G11 -> -127.11025 | I50: ='retained earnings schedule'!H11 -> -123.24297
B51: Dividends paid to non-controlling shareholders of subsidiaries | C51: -32.6 | D51: -43.5 | E51: ='non-controlling interests '!D6 -> -36.85493 | F51: ='non-controlling interests '!E6 -> -34.565098 | G51: ='non-controlling interests '!F6 -> -32.698123 | H51: ='non-controlling interests '!G6 -> -31.274298 | I51: ='non-controlling interests '!H6 -> -30.32279
B52: Purchase of treasury shares | C52: -0.2 | D52: -0.2 | E52: 0 | F52: 0 | G52: 0 | H52: 0 | I52: 0
B53: Interest paid | C53: -30.4 | D53: -53 | E53: =-('debt schedule'!D7) -> -59.887796 | F53: =-('debt schedule'!E7) -> -59.887796 | G53: =-('debt schedule'!F7) -> -59.887796 | H53: =-('debt schedule'!G7) -> -59.887796 | I53: =-('debt schedule'!H7) -> -59.887796
B54: Financing Cash Flow | C54: =SUM(C45:C53) -> 458.7 | D54: =SUM(D45:D53) -> 26.2 | E54: =SUM(E45:E53) -> -246.53472 | F54: =SUM(F45:F53) -> -234.93817 | G54: =SUM(G45:G53) -> -225.48312 | H54: =SUM(H45:H53) -> -218.27234 | I54: =SUM(I45:I53) -> -213.45356
B55: beginning cash flow | C55: 856.9 | D55: 892.4 | E55: ='balance sheet'!H6 -> 868.4 | F55: ='balance sheet'!I6 -> 741.99056 | G55: ='balance sheet'!J6 -> 635.62806 | H55: ='balance sheet'!K6 -> 545.56337 | I55: ='balance sheet'!L6 -> 468.87847
B56: Net Cash Flow | C56: =SUM(C55,C54,C43,C27) -> 892.6 | D56: =SUM(D55,D54,D43,D27) -> 867.8 | E56: =SUM(E55,E54,E43,E27) -> 741.99056 | F56: =SUM(F55,F54,F43,F27) -> 635.62806 | G56: =SUM(G55,G54,G43,G27) -> 545.56337 | H56: =SUM(H55,H54,H43,H27) -> 468.87847 | I56: =SUM(I55,I54,I43,I27) -> 402.66123

Sheet balance sheet
B3: Balance Sheet
B4: SGD in million | G4: 2024 | H4: 2025 | I4: =H4+1 -> 2026 | J4: =I4+1 -> 2027 | K4: =J4+1 -> 2028 | L4: =K4+1 -> 2029 | M4: =L4+1 -> 2030
B5: Current assets:
B6: Short-term deposits and bank balances | G6: =INDEX('Balance Sheet - Data'!$C$3:$D$57,MATCH('balance sheet'!$B6,'Balance Sheet - Data'!$B$3:$B$57,0),MATCH('balance sheet'!G$4,'Balance Sheet - Data'!$C$2:$D$2,0)) -> 892.4 | H6: =INDEX('Balance Sheet - Data'!$C$3:$D$57,MATCH('balance sheet'!$B6,'Balance Sheet - Data'!$B$3:$B$57,0),MATCH('balance sheet'!H$4,'Balance Sheet - Data'!$C$2:$D$2,0)) -> 868.4 | I6: ='cash Flow'!E56 -> 741.99056 | J6: ='cash Flow'!F56 -> 635.62806 | K6: ='cash Flow'!G56 -> 545.56337 | L6: ='cash Flow'!H56 -> 468.87847 | M6: ='cash Flow'!I56 -> 402.66123
B7: Trade and other receivables | G7: =INDEX('Balance Sheet - Data'!$C$3:$D$57,MATCH('balance sheet'!$B7,'Balance Sheet - Data'!$B$3:$B$57,0),MATCH('balance sheet'!G$4,'Balance Sheet - Data'!$C$2:$D$2,0)) -> 725.7 | H7: =INDEX('Balance Sheet - Data'!$C$3:$D$57,MATCH('balance sheet'!$B7,'Balance Sheet - Data'!$B$3:$B$57,0),MATCH('balance sheet'!H$4,'Balance Sheet - Data'!$C$2:$D$2,0)) -> 774.3 | I7: =H7*(1+'Profit & loss'!E$46) -> 802.06618 | J7: =I7*(1+'Profit & loss'!F$46) -> 818.90345 | K7: =J7*(1+'Profit & loss'!G$46) -> 835.28152 | L7: =K7*(1+'Profit & loss'!H$46) -> 851.98715 | M7: =L7*(1+'Profit & loss'!I$46) -> 869.87888
B8: Prepayments | G8: =INDEX('Balance Sheet - Data'!$C$3:$D$57,MATCH('balance sheet'!$B8,'Balance Sheet - Data'!$B$3:$B$57,0),MATCH('balance sheet'!G$4,'Balance Sheet - Data'!$C$2:$D$2,0)) -> 94 | H8: =INDEX('Balance Sheet - Data'!$C$3:$D$57,MATCH('balance sheet'!$B8,'Balance Sheet - Data'!$B$3:$B$57,0),MATCH('balance sheet'!H$4,'Balance Sheet - Data'!$C$2:$D$2,0)) -> 90.8 | I8: =H8*(1+'Profit & loss'!E$46) -> 94.056063 | J8: =I8*(1+'Profit & loss'!F$46) -> 96.030522 | K8: =J8*(1+'Profit & loss'!G$46) -> 97.951133 | L8: =K8*(1+'Profit & loss'!H$46) -> 99.910155 | M8: =L8*(1+'Profit & loss'!I$46) -> 102.00827
B9: Inventories | G9: =INDEX('Balance Sheet - Data'!$C$3:$D$57,MATCH('balance sheet'!$B9,'Balance Sheet - Data'!$B$3:$B$57,0),MATCH('balance sheet'!G$4,'Balance Sheet - Data'!$C$2:$D$2,0)) -> 158 | H9: =INDEX('Balance Sheet - Data'!$C$3:$D$57,MATCH('balance sheet'!$B9,'Balance Sheet - Data'!$B$3:$B$57,0),MATCH('balance sheet'!H$4,'Balance Sheet - Data'!$C$2:$D$2,0)) -> 151.3 | I9: =H9*(1+'Profit & loss'!E$46) -> 156.72558 | J9: =I9*(1+'Profit & loss'!F$46) -> 160.01562 | K9: =J9*(1+'Profit & loss'!G$46) -> 163.21593 | L9: =K9*(1+'Profit & loss'!H$46) -> 166.48025 | M9: =L9*(1+'Profit & loss'!I$46) -> 169.97633
B10: Assets held for sale | G10: =INDEX('Balance Sheet - Data'!$C$3:$D$57,MATCH('balance sheet'!$B10,'Balance Sheet - Data'!$B$3:$B$57,0),MATCH('balance sheet'!G$4,'Balance Sheet - Data'!$C$2:$D$2,0)) -> 29 | H10: =INDEX('Balance Sheet - Data'!$C$3:$D$57,MATCH('balance sheet'!$B10,'Balance Sheet - Data'!$B$3:$B$57,0),MATCH('balance sheet'!H$4,'Balance Sheet - Data'!$C$2:$D$2,0)) -> 0
B11: Total current assets | G11: =SUM(G6:G10) -> 1899.1 | H11: =SUM(H6:H10) -> 1884.8 | I11: =SUM(I6:I10) -> 1794.8384 | J11: =SUM(J6:J10) -> 1710.5777 | K11: =SUM(K6:K10) -> 1642.012 | L11: =SUM(L6:L10) -> 1587.256 | M11: =SUM(M6:M10) -> 1544.5247
B13: Non-current assets:
B14: Associates and joint ventures | G14: =INDEX('Balance Sheet - Data'!$C$3:$D$57,MATCH('balance sheet'!$B14,'Balance Sheet - Data'!$B$3:$B$57,0),MATCH('balance sheet'!G$4,'Balance Sheet - Data'!$C$2:$D$2,0)) -> 12.9 | H14: =INDEX('Balance Sheet - Data'!$C$3:$D$57,MATCH('balance sheet'!$B14,'Balance Sheet - Data'!$B$3:$B$57,0),MATCH('balance sheet'!H$4,'Balance Sheet - Data'!$C$2:$D$2,0)) -> 14.3 | I14: 14.3 | J14: 14.3 | K14: 14.3 | L14: 14.3 | M14: 14.3
B15: Investments | G15: =INDEX('Balance Sheet - Data'!$C$3:$D$57,MATCH('balance sheet'!$B15,'Balance Sheet - Data'!$B$3:$B$57,0),MATCH('balance sheet'!G$4,'Balance Sheet - Data'!$C$2:$D$2,0)) -> 29.1 | H15: =INDEX('Balance Sheet - Data'!$C$3:$D$57,MATCH('balance sheet'!$B15,'Balance Sheet - Data'!$B$3:$B$57,0),MATCH('balance sheet'!H$4,'Balance Sheet - Data'!$C$2:$D$2,0)) -> 27.6 | I15: 27.6 | J15: 27.6 | K15: 27.6 | L15: 27.6 | M15: 27.6
B16: Trade and other receivables | G16: =INDEX('Balance Sheet - Data'!$C$3:$D$57,MATCH('balance sheet'!$B16,'Balance Sheet - Data'!$B$3:$B$57,0),MATCH('balance sheet'!G$4,'Balance Sheet - Data'!$C$2:$D$2,0)) -> 127.7 | H16: =INDEX('Balance Sheet - Data'!$C$3:$D$57,MATCH('balance sheet'!$B16,'Balance Sheet - Data'!$B$3:$B$57,0),MATCH('balance sheet'!H$4,'Balance Sheet - Data'!$C$2:$D$2,0)) -> 268.9 | I16: 268.9 | J16: 268.9 | K16: 268.9 | L16: 268.9 | M16: 268.9
B17: Vehicles, premises and equipment | G17: =INDEX('Balance Sheet - Data'!$C$3:$D$57,MATCH('balance sheet'!$B17,'Balance Sheet - Data'!$B$3:$B$57,0),MATCH('balance sheet'!G$4,'Balance Sheet - Data'!$C$2:$D$2,0)) -> 2129.6 | H17: =INDEX('Balance Sheet - Data'!$C$3:$D$57,MATCH('balance sheet'!$B17,'Balance Sheet - Data'!$B$3:$B$57,0),MATCH('balance sheet'!H$4,'Balance Sheet - Data'!$C$2:$D$2,0)) -> 2339.3 | I17: ='Fixed assets schedule'!E6 -> 2533.1289 | J17: ='Fixed assets schedule'!F6 -> 2705.6379 | K17: ='Fixed assets schedule'!G6 -> 2860.2214 | L17: ='Fixed assets schedule'!H6 -> 3000.2707 | M17: ='Fixed assets schedule'!I6 -> 3129.2292
B18: Intangible assets | G18: =INDEX('Balance Sheet - Data'!$C$3:$D$57,MATCH('balance sheet'!$B18,'Balance Sheet - Data'!$B$3:$B$57,0),MATCH('balance sheet'!G$4,'Balance Sheet - Data'!$C$2:$D$2,0)) -> 557.8 | H18: =INDEX('Balance Sheet - Data'!$C$3:$D$57,MATCH('balance sheet'!$B18,'Balance Sheet - Data'!$B$3:$B$57,0),MATCH('balance sheet'!H$4,'Balance Sheet - Data'!$C$2:$D$2,0)) -> 557.3 | I18: =H18+('Profit & loss'!E32-'Fixed assets schedule'!E5) -> 530.36765 | J18: =I18+('Profit & loss'!F32-'Fixed assets schedule'!F5) -> 502.86992 | K18: =J18+('Profit & loss'!G32-'Fixed assets schedule'!G5) -> 474.82224 | L18: =K18+('Profit & loss'!H32-'Fixed assets schedule'!H5) -> 446.2136 | M18: =L18+('Profit & loss'!I32-'Fixed assets schedule'!I5) -> 417.00419
B19: Goodwill | G19: =INDEX('Balance Sheet - Data'!$C$3:$D$57,MATCH('balance sheet'!$B19,'Balance Sheet - Data'!$B$3:$B$57,0),MATCH('balance sheet'!G$4,'Balance Sheet - Data'!$C$2:$D$2,0)) -> 955.5 | H19: =INDEX('Balance Sheet - Data'!$C$3:$D$57,MATCH('balance sheet'!$B19,'Balance Sheet - Data'!$B$3:$B$57,0),MATCH('balance sheet'!H$4,'Balance Sheet - Data'!$C$2:$D$2,0)) -> 977.1 | I19: 977.1 | J19: 977.1 | K19: 977.1 | L19: 977.1 | M19: 977.1
B20: Deferred tax assets | G20: =INDEX('Balance Sheet - Data'!$C$3:$D$57,MATCH('balance sheet'!$B20,'Balance Sheet - Data'!$B$3:$B$57,0),MATCH('balance sheet'!G$4,'Balance Sheet - Data'!$C$2:$D$2,0)) -> 69.2 | H20: =INDEX('Balance Sheet - Data'!$C$3:$D$57,MATCH('balance sheet'!$B20,'Balance Sheet - Data'!$B$3:$B$57,0),MATCH('balance sheet'!H$4,'Balance Sheet - Data'!$C$2:$D$2,0)) -> 69.6 | I20: 69.6 | J20: 69.6 | K20: 69.6 | L20: 69.6 | M20: 69.6
B21: Total Non-current Assets | G21: =SUM(G14:G20) -> 3881.8 | H21: =SUM(H14:H20) -> 4254.1 | I21: =SUM(I14:I20) -> 4420.9965 | J21: =SUM(J14:J20) -> 4566.0078 | K21: =SUM(K14:K20) -> 4692.5436 | L21: =SUM(L14:L20) -> 4803.9843 | M21: =SUM(M14:M20) -> 4903.7334
B23: Total assets | G23: =SUM(G21,G11) -> 5780.9 | H23: =SUM(H21,H11) -> 6138.9 | I23: =SUM(I21,I11) -> 6215.8349 | J23: =SUM(J21,J11) -> 6276.5855 | K23: =SUM(K21,K11) -> 6334.5556 | L23: =SUM(L21,L11) -> 6391.2404 | M23: =SUM(M21,M11) -> 6448.2581
B26: Current liabilities
B27: Borrowings | G27: =INDEX('Balance Sheet - Data'!$C$3:$D$57,MATCH('balance sheet'!$B27,'Balance Sheet - Data'!$B$3:$B$57,0),MATCH('balance sheet'!G$4,'Balance Sheet - Data'!$C$2:$D$2,0)) -> 590.5 | H27: =INDEX('Balance Sheet - Data'!$C$3:$D$57,MATCH('balance sheet'!$B27,'Balance Sheet - Data'!$B$3:$B$57,0),MATCH('balance sheet'!H$4,'Balance Sheet - Data'!$C$2:$D$2,0)) -> 387.4 | I27: 387.4 | J27: 387.4 | K27: 387.4 | L27: 387.4 | M27: 387.4
B28: Lease liabilities from financial institutions | G28: =INDEX('Balance Sheet - Data'!$C$3:$D$57,MATCH('balance sheet'!$B28,'Balance Sheet - Data'!$B$3:$B$57,0),MATCH('balance sheet'!G$4,'Balance Sheet - Data'!$C$2:$D$2,0)) -> 4.7 | H28: =INDEX('Balance Sheet - Data'!$C$3:$D$57,MATCH('balance sheet'!$B28,'Balance Sheet - Data'!$B$3:$B$57,0),MATCH('balance sheet'!H$4,'Balance Sheet - Data'!$C$2:$D$2,0)) -> 5.3 | I28: 5.3 | J28: 5.3 | K28: 5.3 | L28: 5.3 | M28: 5.3
B29: Lease liabilities | G29: =INDEX('Balance Sheet - Data'!$C$3:$D$57,MATCH('balance sheet'!$B29,'Balance Sheet - Data'!$B$3:$B$57,0),MATCH('balance sheet'!G$4,'Balance Sheet - Data'!$C$2:$D$2,0)) -> 66.1 | H29: =INDEX('Balance Sheet - Data'!$C$3:$D$57,MATCH('balance sheet'!$B29,'Balance Sheet - Data'!$B$3:$B$57,0),MATCH('balance sheet'!H$4,'Balance Sheet - Data'!$C$2:$D$2,0)) -> 60.1 | I29: 60.1 | J29: 60.1 | K29: 60.1 | L29: 60.1 | M29: 60.1
B30: Trade and other payables | G30: =INDEX('Balance Sheet - Data'!$C$3:$D$57,MATCH('balance sheet'!$B30,'Balance Sheet - Data'!$B$3:$B$57,0),MATCH('balance sheet'!G$4,'Balance Sheet - Data'!$C$2:$D$2,0)) -> 1001.1 | H30: =INDEX('Balance Sheet - Data'!$C$3:$D$57,MATCH('balance sheet'!$B30,'Balance Sheet - Data'!$B$3:$B$57,0),MATCH('balance sheet'!H$4,'Balance Sheet - Data'!$C$2:$D$2,0)) -> 954.2 | I30: =H30*(1+'Profit & loss'!E$46) -> 988.41735 | J30: =I30*(1+'Profit & loss'!F$46) -> 1009.1666 | K30: =J30*(1+'Profit & loss'!G$46) -> 1029.3499 | L30: =K30*(1+'Profit & loss'!H$46) -> 1049.9369 | M30: =L30*(1+'Profit & loss'!I$46) -> 1071.9856
B31: Deferred grants | G31: =INDEX('Balance Sheet - Data'!$C$3:$D$57,MATCH('balance sheet'!$B31,'Balance Sheet - Data'!$B$3:$B$57,0),MATCH('balance sheet'!G$4,'Balance Sheet - Data'!$C$2:$D$2,0)) -> 1.1 | H31: =INDEX('Balance Sheet - Data'!$C$3:$D$57,MATCH('balance sheet'!$B31,'Balance Sheet - Data'!$B$3:$B$57,0),MATCH('balance sheet'!H$4,'Balance Sheet - Data'!$C$2:$D$2,0)) -> 0.7 | I31: 0.7 | J31: 0.7 | K31: 0.7 | L31: 0.7 | M31: 0.7
B32: Fuel price equalisation account | G32: =INDEX('Balance Sheet - Data'!$C$3:$D$57,MATCH('balance sheet'!$B32,'Balance Sheet - Data'!$B$3:$B$57,0),MATCH('balance sheet'!G$4,'Balance Sheet - Data'!$C$2:$D$2,0)) -> 19.4 | H32: =INDEX('Balance Sheet - Data'!$C$3:$D$57,MATCH('balance sheet'!$B32,'Balance Sheet - Data'!$B$3:$B$57,0),MATCH('balance sheet'!H$4,'Balance Sheet - Data'!$C$2:$D$2,0)) -> 19.4 | I32: 19.4 | J32: 19.4 | K32: 19.4 | L32: 19.4 | M32: 19.4
B33: Provision for accident claims | G33: =INDEX('Balance Sheet - Data'!$C$3:$D$57,MATCH('balance sheet'!$B33,'Balance Sheet - Data'!$B$3:$B$57,0),MATCH('balance sheet'!G$4,'Balance Sheet - Data'!$C$2:$D$2,0)) -> 45 | H33: =INDEX('Balance Sheet - Data'!$C$3:$D$57,MATCH('balance sheet'!$B33,'Balance Sheet - Data'!$B$3:$B$57,0),MATCH('balance sheet'!H$4,'Balance Sheet - Data'!$C$2:$D$2,0)) -> 50 | I33: 50 | J33: 50 | K33: 50 | L33: 50 | M33: 50
B34: Income tax payable | G34: =INDEX('Balance Sheet - Data'!$C$3:$D$57,MATCH('balance sheet'!$B34,'Balance Sheet - Data'!$B$3:$B$57,0),MATCH('balance sheet'!G$4,'Balance Sheet - Data'!$C$2:$D$2,0)) -> 72.8 | H34: =INDEX('Balance Sheet - Data'!$C$3:$D$57,MATCH('balance sheet'!$B34,'Balance Sheet - Data'!$B$3:$B$57,0),MATCH('balance sheet'!H$4,'Balance Sheet - Data'!$C$2:$D$2,0)) -> 60 | I34: 60 | J34: 60 | K34: 60 | L34: 60 | M34: 60
B35: Total current liabilities | G35: =SUM(G27:G34) -> 1800.7 | H35: =SUM(H27:H34) -> 1537.1 | I35: =SUM(I27:I34) -> 1571.3173 | J35: =SUM(J27:J34) -> 1592.0666 | K35: =SUM(K27:K34) -> 1612.2499 | L35: =SUM(L27:L34) -> 1632.8369 | M35: =SUM(M27:M34) -> 1654.8856
B37: Non-current liabilities
B38: Borrowings | G38: =INDEX('Balance Sheet - Data'!$C$3:$D$57,MATCH('balance sheet'!$B38,'Balance Sheet - Data'!$B$3:$B$57,0),MATCH('balance sheet'!G$4,'Balance Sheet - Data'!$C$2:$D$2,0)) -> 491.1 | H38: =INDEX('Balance Sheet - Data'!$C$3:$D$57,MATCH('balance sheet'!$B$38,'Balance Sheet - Data'!$B$3:$B$57,0),MATCH('balance sheet'!$H$4,'Balance Sheet - Data'!$C$2:$D$2,0)) -> 1184.8 | I38: =INDEX('Balance Sheet - Data'!$C$3:$D$57,MATCH('balance sheet'!$B$38,'Balance Sheet - Data'!$B$3:$B$57,0),MATCH('balance sheet'!$H$4,'Balance Sheet - Data'!$C$2:$D$2,0)) -> 1184.8 | J38: =INDEX('Balance Sheet - Data'!$C$3:$D$57,MATCH('balance sheet'!$B$38,'Balance Sheet - Data'!$B$3:$B$57,0),MATCH('balance sheet'!$H$4,'Balance Sheet - Data'!$C$2:$D$2,0)) -> 1184.8 | K38: =INDEX('Balance Sheet - Data'!$C$3:$D$57,MATCH('balance sheet'!$B$38,'Balance Sheet - Data'!$B$3:$B$57,0),MATCH('balance sheet'!$H$4,'Balance Sheet - Data'!$C$2:$D$2,0)) -> 1184.8 | L38: =INDEX('Balance Sheet - Data'!$C$3:$D$57,MATCH('balance sheet'!$B$38,'Balance Sheet - Data'!$B$3:$B$57,0),MATCH('balance sheet'!$H$4,'Balance Sheet - Data'!$C$2:$D$2,0)) -> 1184.8 | M38: =INDEX('Balance Sheet - Data'!$C$3:$D$57,MATCH('balance sheet'!$B$38,'Balance Sheet - Data'!$B$3:$B$57,0),MATCH('balance sheet'!$H$4,'Balance Sheet - Data'!$C$2:$D$2,0)) -> 1184.8
B39: Lease liabilities from financial institutions | G39: =INDEX('Balance Sheet - Data'!$C$3:$D$57,MATCH('balance sheet'!$B39,'Balance Sheet - Data'!$B$3:$B$57,0),MATCH('balance sheet'!G$4,'Balance Sheet - Data'!$C$2:$D$2,0)) -> 24.3 | H39: =INDEX('Balance Sheet - Data'!$C$3:$D$57,MATCH('balance sheet'!$B39,'Balance Sheet - Data'!$B$3:$B$57,0),MATCH('balance sheet'!H$4,'Balance Sheet - Data'!$C$2:$D$2,0)) -> 21 | I39: 21 | J39: 21 | K39: 21 | L39: 21 | M39: 21
B40: Lease liabilities | G40: =INDEX('Balance Sheet - Data'!$C$3:$D$57,MATCH('balance sheet'!$B40,'Balance Sheet - Data'!$B$3:$B$57,0),MATCH('balance sheet'!G$4,'Balance Sheet - Data'!$C$2:$D$2,0)) -> 177.9 | H40: =INDEX('Balance Sheet - Data'!$C$3:$D$57,MATCH('balance sheet'!$B40,'Balance Sheet - Data'!$B$3:$B$57,0),MATCH('balance sheet'!H$4,'Balance Sheet - Data'!$C$2:$D$2,0)) -> 162.9 | I40: 162.9 | J40: 162.9 | K40: 162.9 | L40: 162.9 | M40: 162.9
B41: Deferred grants | G41: =INDEX('Balance Sheet - Data'!$C$3:$D$57,MATCH('balance sheet'!$B41,'Balance Sheet - Data'!$B$3:$B$57,0),MATCH('balance sheet'!G$4,'Balance Sheet - Data'!$C$2:$D$2,0)) -> 3.7 | H41: =INDEX('Balance Sheet - Data'!$C$3:$D$57,MATCH('balance sheet'!$B41,'Balance Sheet - Data'!$B$3:$B$57,0),MATCH('balance sheet'!H$4,'Balance Sheet - Data'!$C$2:$D$2,0)) -> 2.8 | I41: 2.8 | J41: 2.8 | K41: 2.8 | L41: 2.8 | M41: 2.8
B42: Provision for service benefits and long service award | G42: =INDEX('Balance Sheet - Data'!$C$3:$D$57,MATCH('balance sheet'!$B42,'Balance Sheet - Data'!$B$3:$B$57,0),MATCH('balance sheet'!G$4,'Balance Sheet - Data'!$C$2:$D$2,0)) -> 17.1 | H42: =INDEX('Balance Sheet - Data'!$C$3:$D$57,MATCH('balance sheet'!$B42,'Balance Sheet - Data'!$B$3:$B$57,0),MATCH('balance sheet'!H$4,'Balance Sheet - Data'!$C$2:$D$2,0)) -> 18.5 | I42: =H42+'cash Flow'!E22 -> 17.5 | J42: =I42+'cash Flow'!F22 -> 16.5 | K42: =J42+'cash Flow'!G22 -> 15.5 | L42: =K42+'cash Flow'!H22 -> 14.5 | M42: =L42+'cash Flow'!I22 -> 13.5
B43: Other liabilities | G43: =INDEX('Balance Sheet - Data'!$C$3:$D$57,MATCH('balance sheet'!$B43,'Balance Sheet - Data'!$B$3:$B$57,0),MATCH('balance sheet'!G$4,'Balance Sheet - Data'!$C$2:$D$2,0)) -> 58.1 | H43: =INDEX('Balance Sheet - Data'!$C$3:$D$57,MATCH('balance sheet'!$B43,'Balance Sheet - Data'!$B$3:$B$57,0),MATCH('balance sheet'!H$4,'Balance Sheet - Data'!$C$2:$D$2,0)) -> 45.6 | I43: 45.6 | J43: 45.6 | K43: 45.6 | L43: 45.6 | M43: 45.6
B44: Fuel price equalisation account | G44: =INDEX('Balance Sheet - Data'!$C$3:$D$57,MATCH('balance sheet'!$B44,'Balance Sheet - Data'!$B$3:$B$57,0),MATCH('balance sheet'!G$4,'Balance Sheet - Data'!$C$2:$D$2,0)) -> 19.4 | H44: =INDEX('Balance Sheet - Data'!$C$3:$D$57,MATCH('balance sheet'!$B44,'Balance Sheet - Data'!$B$3:$B$57,0),MATCH('balance sheet'!H$4,'Balance Sheet - Data'!$C$2:$D$2,0)) -> 19.4 | I44: 19.4 | J44: 19.4 | K44: 19.4 | L44: 19.4 | M44: 19.4
B45: Deferred tax liabilities | G45: =INDEX('Balance Sheet - Data'!$C$3:$D$57,MATCH('balance sheet'!$B45,'Balance Sheet - Data'!$B$3:$B$57,0),MATCH('balance sheet'!G$4,'Balance Sheet - Data'!$C$2:$D$2,0)) -> 163 | H45: =INDEX('Balance Sheet - Data'!$C$3:$D$57,MATCH('balance sheet'!$B45,'Balance Sheet - Data'!$B$3:$B$57,0),MATCH('balance sheet'!H$4,'Balance Sheet - Data'!$C$2:$D$2,0)) -> 166.1 | I45: 166.1 | J45: 166.1 | K45: 166.1 | L45: 166.1 | M45: 166.1
B46: Total non-current liabilities | G46: =SUM(G38:G45) -> 954.6 | H46: =SUM(H38:H45) -> 1621.1 | I46: =SUM(I38:I45) -> 1620.1 | J46: =SUM(J38:J45) -> 1619.1 | K46: =SUM(K38:K45) -> 1618.1 | L46: =SUM(L38:L45) -> 1617.1 | M46: =SUM(M38:M45) -> 1616.1
B48: Total liabilites | G48: =SUM(G46,G35) -> 2755.3 | H48: =SUM(H46,H35) -> 3158.2 | I48: =SUM(I46,I35) -> 3191.4173 | J48: =SUM(J46,J35) -> 3211.1666 | K48: =SUM(K46,K35) -> 3230.3499 | L48: =SUM(L46,L35) -> 3249.9369 | M48: =SUM(M46,M35) -> 3270.9856
B50: Share capital | G50: =INDEX('Balance Sheet - Data'!$C$3:$D$57,MATCH('balance sheet'!$B50,'Balance Sheet - Data'!$B$3:$B$57,0),MATCH('balance sheet'!G$4,'Balance Sheet - Data'!$C$2:$D$2,0)) -> 694.4 | H50: =INDEX('Balance Sheet - Data'!$C$3:$D$57,MATCH('balance sheet'!$B50,'Balance Sheet - Data'!$B$3:$B$57,0),MATCH('balance sheet'!H$4,'Balance Sheet - Data'!$C$2:$D$2,0)) -> 694.4 | I50: 694.4 | J50: 694.4 | K50: 694.4 | L50: 694.4 | M50: 694.4
B51: Treasury shares | G51: =INDEX('Balance Sheet - Data'!$C$3:$D$57,MATCH('balance sheet'!$B51,'Balance Sheet - Data'!$B$3:$B$57,0),MATCH('balance sheet'!G$4,'Balance Sheet - Data'!$C$2:$D$2,0)) -> -1.6 | H51: =INDEX('Balance Sheet - Data'!$C$3:$D$57,MATCH('balance sheet'!$B51,'Balance Sheet - Data'!$B$3:$B$57,0),MATCH('balance sheet'!H$4,'Balance Sheet - Data'!$C$2:$D$2,0)) -> -0.8 | I51: -0.8 | J51: -0.8 | K51: -0.8 | L51: -0.8 | M51: -0.8
B52: Other reserves | G52: =INDEX('Balance Sheet - Data'!$C$3:$D$57,MATCH('balance sheet'!$B52,'Balance Sheet - Data'!$B$3:$B$57,0),MATCH('balance sheet'!G$4,'Balance Sheet - Data'!$C$2:$D$2,0)) -> 103.2 | H52: =INDEX('Balance Sheet - Data'!$C$3:$D$57,MATCH('balance sheet'!$B52,'Balance Sheet - Data'!$B$3:$B$57,0),MATCH('balance sheet'!H$4,'Balance Sheet - Data'!$C$2:$D$2,0)) -> 19.4 | I52: 19.4 | J52: 19.4 | K52: 19.4 | L52: 19.4 | M52: 19.4
B53: Foreign currency translation reserve | G53: =INDEX('Balance Sheet - Data'!$C$3:$D$57,MATCH('balance sheet'!$B53,'Balance Sheet - Data'!$B$3:$B$57,0),MATCH('balance sheet'!G$4,'Balance Sheet - Data'!$C$2:$D$2,0)) -> -206.7 | H53: =INDEX('Balance Sheet - Data'!$C$3:$D$57,MATCH('balance sheet'!$B53,'Balance Sheet - Data'!$B$3:$B$57,0),MATCH('balance sheet'!H$4,'Balance Sheet - Data'!$C$2:$D$2,0)) -> -179.6 | I53: -179.6 | J53: -179.6 | K53: -179.6 | L53: -179.6 | M53: -179.6
B54: Retained earnings | G54: =INDEX('Balance Sheet - Data'!$C$3:$D$57,MATCH('balance sheet'!$B54,'Balance Sheet - Data'!$B$3:$B$57,0),MATCH('balance sheet'!G$4,'Balance Sheet - Data'!$C$2:$D$2,0)) -> 2009.7 | H54: =INDEX('Balance Sheet - Data'!$C$3:$D$57,MATCH('balance sheet'!$B54,'Balance Sheet - Data'!$B$3:$B$57,0),MATCH('balance sheet'!H$4,'Balance Sheet - Data'!$C$2:$D$2,0)) -> 2062.1 | I54: ='retained earnings schedule'!D12 -> 2107.4273 | J54: ='retained earnings schedule'!E12 -> 2149.9384 | K54: ='retained earnings schedule'!F12 -> 2190.1534 | L54: ='retained earnings schedule'!G12 -> 2228.6171 | M54: ='retained earnings schedule'!H12 -> 2265.9107
B55: Equity attributable to shareholders of the Company | G55: =INDEX('Balance Sheet - Data'!$C$3:$D$57,MATCH('balance sheet'!$B55,'Balance Sheet - Data'!$B$3:$B$57,0),MATCH('balance sheet'!G$4,'Balance Sheet - Data'!$C$2:$D$2,0)) -> 0 | H55: =INDEX('Balance Sheet - Data'!$C$3:$D$57,MATCH('balance sheet'!$B55,'Balance Sheet - Data'!$B$3:$B$57,0),MATCH('balance sheet'!H$4,'Balance Sheet - Data'!$C$2:$D$2,0)) -> 0
B56: Non-controlling interests | G56: =INDEX('Balance Sheet - Data'!$C$3:$D$57,MATCH('balance sheet'!$B56,'Balance Sheet - Data'!$B$3:$B$57,0),MATCH('balance sheet'!G$4,'Balance Sheet - Data'!$C$2:$D$2,0)) -> 426.6 | H56: =INDEX('Balance Sheet - Data'!$C$3:$D$57,MATCH('balance sheet'!$B56,'Balance Sheet - Data'!$B$3:$B$57,0),MATCH('balance sheet'!H$4,'Balance Sheet - Data'!$C$2:$D$2,0)) -> 385.2 | I56: ='non-controlling interests '!D9 -> 383.59024 | J56: ='non-controlling interests '!E9 -> 382.0805 | K56: ='non-controlling interests '!F9 -> 380.65231 | L56: ='non-controlling interests '!G9 -> 379.28631 | M56: ='non-controlling interests '!H9 -> 377.96186
B57: Total equity | G57: =SUM(G50:G56) -> 3025.6 | H57: =SUM(H50:H56) -> 2980.7 | I57: =SUM(I50:I56) -> 3024.4176 | J57: =SUM(J50:J56) -> 3065.4189 | K57: =SUM(K50:K56) -> 3104.2057 | L57: =SUM(L50:L56) -> 3141.3035 | M57: =SUM(M50:M56) -> 3177.2726
B59: Total liabilities and capital | G59: =SUM(G57,G48) -> 5780.9 | H59: =SUM(H57,H48) -> 6138.9 | I59: =SUM(I57,I48) -> 6215.8349 | J59: =SUM(J57,J48) -> 6276.5855 | K59: =SUM(K57,K48) -> 6334.5556 | L59: =SUM(L57,L48) -> 6391.2404 | M59: =SUM(M57,M48) -> 6448.2581

Sheet Fixed assets schedule
B1: Fixed Assets Schedule | C1: Actuals | E1: Forecast
B2: $ in millions | C2: 2024 | D2: =C2+1 -> 2025 | E2: =D2+1 -> 2026 | F2: =E2+1 -> 2027 | G2: =F2+1 -> 2028 | H2: =G2+1 -> 2029 | I2: =H2+1 -> 2030
B3: Beginning PP&E | C3: 2012.1 | D3: =C6 -> 2129.6 | E3: =D6 -> 2339.3 | F3: =E6 -> 2533.1289 | G3: =F6 -> 2705.6379 | H3: =G6 -> 2860.2214 | I3: =H6 -> 3000.2707
B4: Capital Expenditures | C4: ='balance sheet'!G17-C3+(-C5) -> 477.6 | D4: ='balance sheet'!H17-D3+(-D5) -> 583.3 | E4: =D4*(1+'Profit & loss'!E46) -> 604.21698 | F4: =E4*(1+'Profit & loss'!F46) -> 616.90092 | G4: =F4*(1+'Profit & loss'!G46) -> 629.23894 | H4: =G4*(1+'Profit & loss'!H46) -> 641.82372 | I4: =H4*(1+'Profit & loss'!I46) -> 655.30202
B5: Depreciation related to PPE | C5: -360.1 | D5: -373.6 | E5: =E3*E9 -> -410.38809 | F5: =F3*F9 -> -444.39188 | G5: =G3*G9 -> -474.65549 | H5: =H3*H9 -> -501.77437 | I5: =I3*I9 -> -526.34351
B6: Ending PP&E | C6: =SUM(C3:C5) -> 2129.6 | D6: =SUM(D3:D5) -> 2339.3 | E6: =SUM(E3:E5) -> 2533.1289 | F6: =SUM(F3:F5) -> 2705.6379 | G6: =SUM(G3:G5) -> 2860.2214 | H6: =SUM(H3:H5) -> 3000.2707 | I6: =SUM(I3:I5) -> 3129.2292
B8: Fixed Assets Metrics:
B9: D&A related to PP&E as % of beginning PP&E | C9: =C5/C3 -> -0.17896725 | D9: =D5/D3 -> -0.17543201 | E9: -0.17543201 | F9: -0.17543201 | G9: -0.17543201 | H9: -0.17543201 | I9: -0.17543201
B11: Total Depreciation & Amortization
B12: D&A not related to PPE | C12: =('Profit & loss'!C32-'Fixed assets schedule'!C5) -> -8.3 | D12: =('Profit & loss'!D32-'Fixed assets schedule'!D5) -> -26 | E12: =E13*'Profit & loss'!E12 -> -26.932353 | F12: =F13*'Profit & loss'!F12 -> -27.497727 | G12: =G13*'Profit & loss'!G12 -> -28.047681 | H12: =H13*'Profit & loss'!H12 -> -28.608635 | I12: =I13*'Profit & loss'!I12 -> -29.209416
B13: D&A not related to PPE as % of Revenue | C13: =C12/'Profit & loss'!C12 -> -0.0018541271 | D13: =D12/'Profit & loss'!D12 -> -0.005139762 | E13: -0.005139762 | F13: -0.005139762 | G13: -0.005139762 | H13: -0.005139762 | I13: -0.005139762
B14: Total D&A | C14: ='Profit & loss'!C32 -> -368.4 | D14: ='Profit & loss'!D32 -> -399.6 | E14: =E12+E5 -> -437.32044 | F14: =F12+F5 -> -471.88961 | G14: =G12+G5 -> -502.70317 | H14: =H12+H5 -> -530.38301 | I14: =I12+I5 -> -555.55293

Sheet retained earnings schedule
A1: Retained earningss Schedule | B1: Actuals | D1: Forecast
A2: $ in millions | B2: 2024 | C2: =B2+1 -> 2025 | D2: =C2+1 -> 2026 | E2: =D2+1 -> 2027 | F2: =E2+1 -> 2028 | G2: =F2+1 -> 2029 | H2: =G2+1 -> 2030
A3: Beginning retained earnings | B3: 2004.7 | C3: 2009.7 | D3: =C12 -> 2062.1 | E3: =D12 -> 2107.4273 | F3: =E12 -> 2149.9384 | G3: =F12 -> 2190.1534 | H3: =G12 -> 2228.6171
A4: Net income | B4: ='Profit & loss'!C41 -> 255.7 | C4: ='Profit & loss'!D41 -> 271.9 | D4: ='Profit & loss'!E41 -> 230.36449 | E4: ='Profit & loss'!F41 -> 216.05173 | F4: ='Profit & loss'!G41 -> 204.38206 | G4: ='Profit & loss'!H41 -> 195.48233 | H4: ='Profit & loss'!I41 -> 189.53486
A5: less:non controlling interests | B5: -45.2 | C5: -41.6 | D5: =(C5/C4)*D4 -> -35.245174 | E5: =(D5/D4)*E4 -> -33.055358 | F5: =(E5/E4)*F4 -> -31.269929 | G5: =(F5/F4)*G4 -> -29.908294 | H5: =(G5/G4)*H4 -> -28.998346
A6: portion of net income transferred to retained earnings account | B6: =SUM(B4:B5) -> 210.5 | C6: =SUM(C4:C5) -> 230.3 | D6: =SUM(D4:D5) -> 195.11932 | E6: =SUM(E4:E5) -> 182.99637 | F6: =SUM(F4:F5) -> 173.11213 | G6: =SUM(G4:G5) -> 165.57404 | H6: =SUM(H4:H5) -> 160.53652
A7: transfer of asset revaluation reserve on disposal | B7: 30 | C7: 0 | D7: 0 | E7: 0 | F7: 0 | G7: 0 | H7: 0
A8: other reserves | B8: 1 | C8: -1.1 | D8: 0 | E8: 0 | F8: 0 | G8: 0 | H8: 0
A9: transfer of fair velue reserves | B9: -79.3 | C9: 0 | D9: 0 | E9: 0 | F9: 0 | G9: 0 | H9: 0
A10: dividends received | B10: 0.5 | C10: 0 | D10: 0 | E10: 0 | F10: 0 | G10: 0 | H10: 0
A11: Dividends paid | B11: -157.7 | C11: -176.8 | D11: =(C11/C4)*D4 -> -149.79199 | E11: =(D11/D4)*E4 -> -140.48527 | F11: =(E11/E4)*F4 -> -132.8972 | G11: =(F11/F4)*G4 -> -127.11025 | H11: =(G11/G4)*H4 -> -123.24297
A12: Ending retained earnings | B12: =SUM(B3,B6:B11) -> 2009.7 | C12: =SUM(C3,C6:C11) -> 2062.1 | D12: =SUM(D3,D6:D11) -> 2107.4273 | E12: =SUM(E3,E6:E11) -> 2149.9384 | F12: =SUM(F3,F6:F11) -> 2190.1534 | G12: =SUM(G3,G6:G11) -> 2228.6171 | H12: =SUM(H3,H6:H11) -> 2265.9107

Sheet non-controlling interests 
A1: Non controlling interests Schedule | B1: Actuals | D1: Forecast
A2: $ in millions | B2: 2024 | C2: =B2+1 -> 2025 | D2: =C2+1 -> 2026 | E2: =D2+1 -> 2027 | F2: =E2+1 -> 2028 | G2: =F2+1 -> 2029 | H2: =G2+1 -> 2030
A3: Beginning non-controlling interests | B3: 416.2 | C3: 426.6 | D3: =C9 -> 385.2 | E3: =D9 -> 383.59024 | F3: =E9 -> 382.0805 | G3: =F9 -> 380.65231 | H3: =G9 -> 379.28631
A4: Net income | B4: =-'retained earnings schedule'!B5 -> 45.2 | C4: =-'retained earnings schedule'!C5 -> 41.6 | D4: =(C4/'Profit & loss'!D41)*'Profit & loss'!E41 -> 35.245174 | E4: =(D4/'Profit & loss'!E41)*'Profit & loss'!F41 -> 33.055358 | F4: =(E4/'Profit & loss'!F41)*'Profit & loss'!G41 -> 31.269929 | G4: =(F4/'Profit & loss'!G41)*'Profit & loss'!H41 -> 29.908294 | H4: =(G4/'Profit & loss'!H41)*'Profit & loss'!I41 -> 28.998346
A5: other comprehensive income/(loss) | B5: 1.3 | C5: -2.5 | D5: 0 | E5: 0 | F5: 0 | G5: 0 | H5: 0
A6: less:payment of dividends | B6: -32.6 | C6: -43.5 | D6: =(C6/'Profit & loss'!D41)*'Profit & loss'!E41 -> -36.85493 | E6: =(D6/'Profit & loss'!E41)*'Profit & loss'!F41 -> -34.565098 | F6: =(E6/'Profit & loss'!F41)*'Profit & loss'!G41 -> -32.698123 | G6: =(F6/'Profit & loss'!G41)*'Profit & loss'!H41 -> -31.274298 | H6: =(G6/'Profit & loss'!H41)*'Profit & loss'!I41 -> -30.32279
A7: Acquisition of non controlling interests | C7: -39.1 | D7: 0 | E7: 0 | F7: 0 | G7: 0 | H7: 0
A8: other reserves | B8: -3.5 | C8: 2.1 | D8: 0 | E8: 0 | F8: 0 | G8: 0 | H8: 0
A9: ending non controlling interests | B9: =SUM(B3:B8) -> 426.6 | C9: =SUM(C3:C8) -> 385.2 | D9: =SUM(D3:D8) -> 383.59024 | E9: =SUM(E3:E8) -> 382.0805 | F9: =SUM(F3:F8) -> 380.65231 | G9: =SUM(G3:G8) -> 379.28631 | H9: =SUM(H3:H8) -> 377.96186

Sheet debt schedule
A1: Debt Schedule | B1: Actuals | D1: Forecast
A2: $ in millions | B2: 2024 | C2: =B2+1 -> 2025 | D2: =C2+1 -> 2026 | E2: =D2+1 -> 2027 | F2: =E2+1 -> 2028 | G2: =F2+1 -> 2029 | H2: =G2+1 -> 2030
A3: Beginning borrowings | B3: =234.9+115.4 -> 350.3 | C3: ='balance sheet'!G38+'balance sheet'!G27 -> 1081.6 | D3: =C5 -> 1572.2 | E3: =D5 -> 1572.2 | F3: =E5 -> 1572.2 | G3: =F5 -> 1572.2 | H3: =G5 -> 1572.2
A4: additions/(repayments) | B4: =B5-B3 -> 731.3 | C4: =C5-C3 -> 490.6 | D4: 0 | E4: 0 | F4: 0 | G4: 0 | H4: 0
A5: ending borrowings | B5: ='balance sheet'!G27+'balance sheet'!G38 -> 1081.6 | C5: ='balance sheet'!H27+'balance sheet'!H38 -> 1572.2 | D5: ='balance sheet'!I27+'balance sheet'!I38 -> 1572.2 | E5: ='balance sheet'!J27+'balance sheet'!J38 -> 1572.2 | F5: ='balance sheet'!K27+'balance sheet'!K38 -> 1572.2 | G5: ='balance sheet'!L27+'balance sheet'!L38 -> 1572.2 | H5: ='balance sheet'!M27+'balance sheet'!M38 -> 1572.2
A6: Implied interest rate | B6: =B7/B3 -> 0.089351984 | C6: =C7/C3 -> 0.038091716 | D6: 0.038091716 | E6: 0.038091716 | F6: 0.038091716 | G6: 0.038091716 | H6: 0.038091716
A7: loan interest expense | B7: 31.3 | C7: 41.2 | D7: =D6*D3 -> 59.887796 | E7: =E6*E3 -> 59.887796 | F7: =F6*F3 -> 59.887796 | G7: =G6*G3 -> 59.887796 | H7: =H6*H3 -> 59.887796
A9: Beginning lease liabilities | B9: =8.1+31.5+1+137.3 -> 177.9 | C9: ='debt schedule'!B11 -> 273 | D9: =C11 -> 249.3 | E9: =D11 -> 249.3 | F9: =E11 -> 249.3 | G9: =F11 -> 249.3 | H9: =G11 -> 249.3
A10: additions/(repayments) | B10: =B11-B9 -> 95.1 | C10: =C11-C9 -> -23.7 | D10: =D11-D9 -> 0 | E10: =E11-E9 -> 0 | F10: =F11-F9 -> 0 | G10: =G11-G9 -> 0 | H10: =H11-H9 -> 0
A11: ending lease liabilities | B11: ='balance sheet'!G28+'balance sheet'!G29+'balance sheet'!G39+'balance sheet'!G40 -> 273 | C11: ='balance sheet'!H28+'balance sheet'!H29+'balance sheet'!H39+'balance sheet'!H40 -> 249.3 | D11: ='balance sheet'!I28+'balance sheet'!I29+'balance sheet'!I39+'balance sheet'!I40 -> 249.3 | E11: ='balance sheet'!J28+'balance sheet'!J29+'balance sheet'!J39+'balance sheet'!J40 -> 249.3 | F11: ='balance sheet'!K28+'balance sheet'!K29+'balance sheet'!K39+'balance sheet'!K40 -> 249.3 | G11: ='balance sheet'!L28+'balance sheet'!L29+'balance sheet'!L39+'balance sheet'!L40 -> 249.3 | H11: ='balance sheet'!M28+'balance sheet'!M29+'balance sheet'!M39+'balance sheet'!M40 -> 249.3
A12: Implied interest rate | B12: =B13/B9 -> 0.04272063 | C12: =C13/C9 -> 0.042490842 | D12: 0.042490842 | E12: 0.042490842 | F12: 0.042490842 | G12: 0.042490842 | H12: 0.042490842
A13: lease liabilities interest expense | B13: 7.6 | C13: 11.6 | D13: =D9*D12 -> 10.592967 | E13: =E9*E12 -> 10.592967 | F13: =F9*F12 -> 10.592967 | G13: =G9*G12 -> 10.592967 | H13: =H9*H12 -> 10.592967

Sheet data source--->

Sheet Income Statement - Data
B2: Income Statement | C2: 2025 | D2: 2024
B3: Net Sales | C3: 5058.6 | D3: 4476.5
B4: Operating expenses
B5: Staff costs | C5: -2272 | D5: -2024.1
B6: Contract services and subcontractor costs | C6: -644.3 | D6: -445.8
B7: Fuel and electricity costs | C7: -350.9 | D7: -397.2
B8: Repairs and maintenance costs | C8: -349.3 | D8: -329.7
B9: Materials and consumables costs | C9: -90 | D9: -104.4
B10: Insurance premiums and accident claims | C10: -122.6 | D10: -102.1
B11: Premises costs | C11: -97.5 | D11: -86.8
B12: Road tax and licence fees | C12: -85.7 | D12: -74.6
B13: Utilities,It and communication costs | C13: -90.6 | D13: -73.5
B14: Taxi drivers’ benefits | C14: -70.4 | D14: -12
B15: Advertising production and promotion costs | C15: -36 | D15: -34.5
B16: Professional fees | C16: -30.8 | D16: -33.2
B17: Impairment of good will | C17: -2.1 | D17: –
B18: Net gain on disposal of vehicles,premises and equipment | C18: 25.9 | D18: 5.1
B19: Other operating costs | C19: -69.7 | D19: -72.4
B20: Total operating costs | C20: =SUM(C5:C19) -> -4286 | D20: =SUM(D5:D19) -> -3785.2
B22: EBIT | C22: =SUM(C3,C20) -> 772.6 | D22: =SUM(D3,D20) -> 691.3
B23: Depreciation and amortisation | C23: -399.6 | D23: -368.4
B24: EBITDA | C24: =SUM(C22:C23) -> 373 | D24: =SUM(D22:D23) -> 322.9
B26: Other income/(costs)
B27: Investments income | C27: 20.4 | D27: 31.7
B28: Finance costs | C28: -52.8 | D28: -38.9
B29: Share of results of associates and joint ventures | C29: 0.8 | D29: 1.8
B31: EBT | C31: =SUM(C24,C27:C29) -> 341.4 | D31: =SUM(D24,D27:D29) -> 317.5
B32: Taxation | C32: -69.5 | D32: -61.8
B33: profit after taxation | C33: =SUM(C31:C32) -> 271.9 | D33: =SUM(D31:D32) -> 255.7

Sheet Balance Sheet - Data
B2: Balance Sheet | C2: 2025 | D2: 2024
B3: Current assets:
B4: Short-term deposits and bank balances | C4: 868.4 | D4: 892.4
B5: Trade and other receivables | C5: 774.3 | D5: 725.7
B6: Prepayments | C6: 90.8 | D6: 94
B7: Inventories | C7: 151.3 | D7: 158
B8: Assets held for sale | D8: 29
B9: Total current assets | C9: =SUM(C4:C7) -> 1884.8 | D9: =SUM(D4:D8) -> 1899.1
B11: Non-current assets:
B12: Associates and joint ventures | C12: 14.3 | D12: 12.9
B13: Investments | C13: 27.6 | D13: 29.1
B14: Trade and other receivables | C14: 268.9 | D14: 127.7
B15: Vehicles, premises and equipment | C15: 2339.3 | D15: 2129.6
B16: Intangible assets | C16: 557.3 | D16: 557.8
B17: Goodwill | C17: 977.1 | D17: 955.5
B18: Deferred tax assets | C18: 69.6 | D18: 69.2
B19: Total Non-current Assets | C19: =SUM(C12:C18) -> 4254.1 | D19: =SUM(D12:D18) -> 3881.8
B21: Total assets | C21: =SUM(C19,C9) -> 6138.9 | D21: =SUM(D19,D9) -> 5780.9
B24: Current liabilities
B25: Borrowings | C25: 387.4 | D25: 590.5
B26: Lease liabilities from financial institutions | C26: 5.3 | D26: 4.7
B27: Lease liabilities | C27: 60.1 | D27: 66.1
B28: Trade and other payables | C28: 954.2 | D28: 1001.1
B29: Deferred grants | C29: 0.7 | D29: 1.1
B30: Fuel price equalisation account | C30: 19.4 | D30: 19.4
B31: Provision for accident claims | C31: 50 | D31: 45
B32: Income tax payable | C32: 60 | D32: 72.8
B33: Total current liabilities | C33: =SUM(C25:C32) -> 1537.1 | D33: =SUM(D25:D32) -> 1800.7
B35: Non-current liabilities
B36: borrowings | C36: 1184.8 | D36: 491.1
B37: Lease liabilities from financial institutions | C37: 21 | D37: 24.3
B38: Lease liabilities | C38: 162.9 | D38: 177.9
B39: Deferred grants | C39: 2.8 | D39: 3.7
B40: Provision for service benefits and long service award | C40: 18.5 | D40: 17.1
B41: Other liabilities | C41: 45.6 | D41: 58.1
B42: Fuel price equalisation account | C42: 19.4 | D42: 19.4
B43: Deferred tax liabilities | C43: 166.1 | D43: 163
B44: Total non-current liabilities | C44: =SUM(C36:C43) -> 1621.1 | D44: =SUM(D36:D43) -> 954.6
B46: Total liabilites | C46: =SUM(C44,C33) -> 3158.2 | D46: =SUM(D44,D33) -> 2755.3
B48: Share capital | C48: 694.4 | D48: 694.4
B49: Treasury shares | C49: -0.8 | D49: -1.6
B50: Other reserves | C50: 19.4 | D50: 103.2
B51: Foreign currency translation reserve | C51: -179.6 | D51: -206.7
B52: Retained earnings | C52: 2062.1 | D52: 2009.7
B53: Equity attributable to shareholders of the Company
B54: Non-controlling interests | C54: 385.2 | D54: 426.6
B55: Total equity | C55: =SUM(C48:C54) -> 2980.7 | D55: =SUM(D48:D54) -> 3025.6
B57: Total liabilities and capital | C57: =SUM(C55,C46) -> 6138.9 | D57: =SUM(D55,D46) -> 5780.9
